<?xml version="1.0" encoding="UTF-8" standalone="yes"?>
<w:document xmlns:wpc="http://schemas.microsoft.com/office/word/2010/wordprocessingCanvas" xmlns:cx="http://schemas.microsoft.com/office/drawing/2014/chartex" xmlns:cx1="http://schemas.microsoft.com/office/drawing/2015/9/8/chartex" xmlns:cx2="http://schemas.microsoft.com/office/drawing/2015/10/21/chartex" xmlns:cx3="http://schemas.microsoft.com/office/drawing/2016/5/9/chartex" xmlns:cx4="http://schemas.microsoft.com/office/drawing/2016/5/10/chartex" xmlns:cx5="http://schemas.microsoft.com/office/drawing/2016/5/11/chartex" xmlns:cx6="http://schemas.microsoft.com/office/drawing/2016/5/12/chartex" xmlns:cx7="http://schemas.microsoft.com/office/drawing/2016/5/13/chartex" xmlns:cx8="http://schemas.microsoft.com/office/drawing/2016/5/14/chartex" xmlns:mc="http://schemas.openxmlformats.org/markup-compatibility/2006" xmlns:aink="http://schemas.microsoft.com/office/drawing/2016/ink" xmlns:am3d="http://schemas.microsoft.com/office/drawing/2017/model3d" xmlns:o="urn:schemas-microsoft-com:office:office" xmlns:oel="http://schemas.microsoft.com/office/2019/extlst" xmlns:r="http://schemas.openxmlformats.org/officeDocument/2006/relationships" xmlns:m="http://schemas.openxmlformats.org/officeDocument/2006/math" xmlns:v="urn:schemas-microsoft-com:vml" xmlns:wp14="http://schemas.microsoft.com/office/word/2010/wordprocessingDrawing" xmlns:wp="http://schemas.openxmlformats.org/drawingml/2006/wordprocessingDrawing" xmlns:w10="urn:schemas-microsoft-com:office:word" xmlns:w="http://schemas.openxmlformats.org/wordprocessingml/2006/main" xmlns:w14="http://schemas.microsoft.com/office/word/2010/wordml" xmlns:w15="http://schemas.microsoft.com/office/word/2012/wordml" xmlns:w16cex="http://schemas.microsoft.com/office/word/2018/wordml/cex" xmlns:w16cid="http://schemas.microsoft.com/office/word/2016/wordml/cid" xmlns:w16="http://schemas.microsoft.com/office/word/2018/wordml" xmlns:w16du="http://schemas.microsoft.com/office/word/2023/wordml/word16du" xmlns:w16sdtdh="http://schemas.microsoft.com/office/word/2020/wordml/sdtdatahash" xmlns:w16sdtfl="http://schemas.microsoft.com/office/word/2024/wordml/sdtformatlock" xmlns:w16se="http://schemas.microsoft.com/office/word/2015/wordml/symex" xmlns:wpg="http://schemas.microsoft.com/office/word/2010/wordprocessingGroup" xmlns:wpi="http://schemas.microsoft.com/office/word/2010/wordprocessingInk" xmlns:wne="http://schemas.microsoft.com/office/word/2006/wordml" xmlns:wps="http://schemas.microsoft.com/office/word/2010/wordprocessingShape" mc:Ignorable="w14 w15 w16se w16cid w16 w16cex w16sdtdh w16sdtfl w16du wp14"><w:body><w:p w14:paraId="63712CB3" w14:textId="77777777" w:rsidR="00EF5116" w:rsidRDefault="00000000"><w:pPr><w:spacing w:after="0" w:line="259" w:lineRule="auto"/><w:ind w:left="0" w:firstLine="0"/></w:pPr><w:r><w:rPr><w:color w:val="000000"/><w:sz w:val="48"/></w:rPr><w:t>Terms &amp; Conditions for the Sale of Goods</w:t></w:r></w:p><w:p w14:paraId="07CCB349" w14:textId="77777777" w:rsidR="00EF5116" w:rsidRDefault="00EF5116"><w:pPr><w:sectPr w:rsidR="00EF5116" w:rsidSect="006E73FE"><w:pgSz w:w="11906" w:h="16838"/><w:pgMar w:top="2189" w:right="2207" w:bottom="3360" w:left="815" w:header="720" w:footer="720" w:gutter="0"/><w:cols w:space="720"/></w:sectPr></w:pPr></w:p><w:p w14:paraId="5306AC58" w14:textId="77777777" w:rsidR="00EF5116" w:rsidRDefault="00000000"><w:pPr><w:spacing w:after="124" w:line="259" w:lineRule="auto"/><w:ind w:left="-5"/></w:pPr><w:r><w:rPr><w:sz w:val="24"/></w:rPr><w:t>Contents:</w:t></w:r></w:p><w:p w14:paraId="420E87FB" w14:textId="77777777" w:rsidR="00EF5116" w:rsidRDefault="00000000"><w:pPr><w:numPr><w:ilvl w:val="0"/><w:numId w:val="1"/></w:numPr><w:spacing w:after="0" w:line="265" w:lineRule="auto"/><w:ind w:hanging="360"/></w:pPr><w:r><w:rPr><w:color w:val="000000"/></w:rPr><w:t>Definitions</w:t></w:r></w:p><w:p w14:paraId="4283841F" w14:textId="77777777" w:rsidR="00EF5116" w:rsidRDefault="00000000"><w:pPr><w:numPr><w:ilvl w:val="0"/><w:numId w:val="1"/></w:numPr><w:spacing w:after="0" w:line="265" w:lineRule="auto"/><w:ind w:hanging="360"/></w:pPr><w:r><w:rPr><w:color w:val="000000"/></w:rPr><w:t>Conditions</w:t></w:r></w:p><w:p w14:paraId="4A706E3B" w14:textId="77777777" w:rsidR="00EF5116" w:rsidRDefault="00000000"><w:pPr><w:numPr><w:ilvl w:val="0"/><w:numId w:val="1"/></w:numPr><w:spacing w:after="0" w:line="265" w:lineRule="auto"/><w:ind w:hanging="360"/></w:pPr><w:r><w:rPr><w:color w:val="000000"/></w:rPr><w:t>Price</w:t></w:r></w:p><w:p w14:paraId="5641A686" w14:textId="77777777" w:rsidR="00EF5116" w:rsidRDefault="00000000"><w:pPr><w:numPr><w:ilvl w:val="0"/><w:numId w:val="1"/></w:numPr><w:spacing w:after="0" w:line="265" w:lineRule="auto"/><w:ind w:hanging="360"/></w:pPr><w:r><w:rPr><w:color w:val="000000"/></w:rPr><w:t>Payment and Interest</w:t></w:r></w:p><w:p w14:paraId="2F9E3B65" w14:textId="77777777" w:rsidR="00EF5116" w:rsidRDefault="00000000"><w:pPr><w:numPr><w:ilvl w:val="0"/><w:numId w:val="1"/></w:numPr><w:spacing w:after="0" w:line="265" w:lineRule="auto"/><w:ind w:hanging="360"/></w:pPr><w:r><w:rPr><w:color w:val="000000"/></w:rPr><w:t>Goods</w:t></w:r></w:p><w:p w14:paraId="64596DED" w14:textId="77777777" w:rsidR="00EF5116" w:rsidRDefault="00000000"><w:pPr><w:numPr><w:ilvl w:val="0"/><w:numId w:val="1"/></w:numPr><w:spacing w:after="0" w:line="265" w:lineRule="auto"/><w:ind w:hanging="360"/></w:pPr><w:r><w:rPr><w:color w:val="000000"/></w:rPr><w:t>Warranties</w:t></w:r></w:p><w:p w14:paraId="55DB0DF0" w14:textId="77777777" w:rsidR="00EF5116" w:rsidRDefault="00000000"><w:pPr><w:numPr><w:ilvl w:val="0"/><w:numId w:val="1"/></w:numPr><w:spacing w:after="0" w:line="265" w:lineRule="auto"/><w:ind w:hanging="360"/></w:pPr><w:r><w:rPr><w:color w:val="000000"/></w:rPr><w:t>Delivery of the Goods</w:t></w:r></w:p><w:p w14:paraId="4FB29F28" w14:textId="77777777" w:rsidR="00EF5116" w:rsidRDefault="00000000"><w:pPr><w:numPr><w:ilvl w:val="0"/><w:numId w:val="1"/></w:numPr><w:spacing w:after="0" w:line="265" w:lineRule="auto"/><w:ind w:hanging="360"/></w:pPr><w:r><w:rPr><w:color w:val="000000"/></w:rPr><w:t>Acceptance of the Goods</w:t></w:r></w:p><w:p w14:paraId="12909BBF" w14:textId="77777777" w:rsidR="00EF5116" w:rsidRDefault="00000000"><w:pPr><w:numPr><w:ilvl w:val="0"/><w:numId w:val="1"/></w:numPr><w:spacing w:after="0" w:line="265" w:lineRule="auto"/><w:ind w:hanging="360"/></w:pPr><w:r><w:rPr><w:color w:val="000000"/></w:rPr><w:t>Title and Risk</w:t></w:r></w:p><w:p w14:paraId="50B3BC89" w14:textId="77777777" w:rsidR="00EF5116" w:rsidRDefault="00000000"><w:pPr><w:numPr><w:ilvl w:val="0"/><w:numId w:val="1"/></w:numPr><w:spacing w:after="459" w:line="265" w:lineRule="auto"/><w:ind w:hanging="360"/></w:pPr><w:r><w:rPr><w:color w:val="000000"/></w:rPr><w:t>Carriage of Goods</w:t></w:r></w:p><w:p w14:paraId="1A54BEEB" w14:textId="77777777" w:rsidR="00EF5116" w:rsidRDefault="00000000"><w:pPr><w:pStyle w:val="Heading1"/><w:ind w:left="-5"/></w:pPr><w:r><w:t>1. Definitions</w:t></w:r></w:p><w:p w14:paraId="402D0D78" w14:textId="77777777" w:rsidR="00EF5116" w:rsidRDefault="00000000"><w:pPr><w:ind w:left="-5"/></w:pPr><w:r><w:t>Buyer the person who buys or agrees to buy the goods from the Seller.</w:t></w:r></w:p><w:p w14:paraId="1B6A951B" w14:textId="77777777" w:rsidR="00EF5116" w:rsidRDefault="00000000"><w:pPr><w:ind w:left="-5"/></w:pPr><w:r><w:t>Conditions the terms and conditions of sale as set out in this document and any special terms and conditions agreed in writing by the Seller.</w:t></w:r></w:p><w:p w14:paraId="62E6DE7C" w14:textId="77777777" w:rsidR="00EF5116" w:rsidRDefault="00000000"><w:pPr><w:ind w:left="-5"/></w:pPr><w:r><w:t>Goods the articles which the Buyer agrees to buy from the Seller.</w:t></w:r></w:p><w:p w14:paraId="4DF2254B" w14:textId="77777777" w:rsidR="00EF5116" w:rsidRDefault="00000000"><w:pPr><w:ind w:left="-5"/></w:pPr><w:r><w:t>Price the price for the Goods, excluding VAT and any carriage, packaging and insurance costs.</w:t></w:r></w:p><w:p w14:paraId="5D8D9DD0" w14:textId="77777777" w:rsidR="00EF5116" w:rsidRDefault="00000000"><w:pPr><w:spacing w:after="563" w:line="216" w:lineRule="auto"/><w:ind w:left="0" w:right="328" w:firstLine="0"/><w:jc w:val="both"/></w:pPr><w:r><w:t>Seller means One2Call Ltd of Unit 2, Longacre Close, Holbrook Industrial Estate, Sheffield, South Yorkshire, S20 3FR.</w:t></w:r></w:p><w:p w14:paraId="1CEC2029" w14:textId="77777777" w:rsidR="00EF5116" w:rsidRDefault="00000000"><w:pPr><w:pStyle w:val="Heading1"/><w:ind w:left="-5"/></w:pPr><w:r><w:t>2. Conditions</w:t></w:r></w:p><w:p w14:paraId="299A9871" w14:textId="77777777" w:rsidR="00EF5116" w:rsidRDefault="00000000"><w:pPr><w:ind w:left="-5"/></w:pPr><w:r><w:t>2.1 These Conditions shall form the basis of the contract between the Seller and the Buyer in relation to the sale of Goods, to the exclusion of all other terms and conditions including the Buyer’s standard conditions of purchase or any other conditions which the Buyer may purport to apply under any purchase order or confirmation of order or any other document.</w:t></w:r></w:p><w:p w14:paraId="2AD6EED5" w14:textId="77777777" w:rsidR="00EF5116" w:rsidRDefault="00000000"><w:pPr><w:ind w:left="-5"/></w:pPr><w:r><w:t>2.2 All orders for Goods shall be deemed to be an offer by the Buyer to purchase Goods from the Seller pursuant to these Conditions.</w:t></w:r></w:p><w:p w14:paraId="12953BAC" w14:textId="77777777" w:rsidR="00EF5116" w:rsidRDefault="00000000"><w:pPr><w:ind w:left="-5"/></w:pPr><w:r><w:t>2.3 Acceptance of delivery of the Goods shall be deemed to be conclusive evidence of the Buyer’s acceptance of these Conditions.</w:t></w:r></w:p><w:p w14:paraId="021EE43E" w14:textId="77777777" w:rsidR="00EF5116" w:rsidRDefault="00000000"><w:pPr><w:spacing w:line="296" w:lineRule="auto"/><w:ind w:left="-5" w:right="353"/></w:pPr><w:r><w:rPr><w:noProof/><w:color w:val="000000"/><w:sz w:val="22"/></w:rPr><mc:AlternateContent><mc:Choice Requires="wpg"><w:drawing><wp:anchor distT="0" distB="0" distL="114300" distR="114300" simplePos="0" relativeHeight="251658240" behindDoc="0" locked="0" layoutInCell="1" allowOverlap="1" wp14:anchorId="5CE3A52A" wp14:editId="24441666"><wp:simplePos x="0" y="0"/><wp:positionH relativeFrom="page"><wp:posOffset>0</wp:posOffset></wp:positionH><wp:positionV relativeFrom="page"><wp:posOffset>0</wp:posOffset></wp:positionV><wp:extent cx="7560005" cy="942873"/><wp:effectExtent l="0" t="0" r="0" b="0"/><wp:wrapTopAndBottom/><wp:docPr id="9109" name="Group 9109"/><wp:cNvGraphicFramePr/><a:graphic xmlns:a="http://schemas.openxmlformats.org/drawingml/2006/main"><a:graphicData uri="http://schemas.microsoft.com/office/word/2010/wordprocessingGroup"><wpg:wgp><wpg:cNvGrpSpPr/><wpg:grpSpPr><a:xfrm><a:off x="0" y="0"/><a:ext cx="7560005" cy="942873"/><a:chOff x="0" y="0"/><a:chExt cx="7560005" cy="942873"/></a:xfrm></wpg:grpSpPr><wps:wsp><wps:cNvPr id="10117" name="Shape 10117"/><wps:cNvSpPr/><wps:spPr><a:xfrm><a:off x="0" y="0"/><a:ext cx="7560005" cy="216002"/></a:xfrm><a:custGeom><a:avLst/><a:gdLst/><a:ahLst/><a:cxnLst/><a:rect l="0" t="0" r="0" b="0"/><a:pathLst><a:path w="7560005" h="216002"><a:moveTo><a:pt x="0" y="0"/></a:moveTo><a:lnTo><a:pt x="7560005" y="0"/></a:lnTo><a:lnTo><a:pt x="7560005" y="216002"/></a:lnTo><a:lnTo><a:pt x="0" y="216002"/></a:lnTo><a:lnTo><a:pt x="0" y="0"/></a:lnTo></a:path></a:pathLst></a:custGeom><a:ln w="0" cap="flat"><a:miter lim="127000"/></a:ln></wps:spPr><wps:style><a:lnRef idx="0"><a:srgbClr val="000000"><a:alpha val="0"/></a:srgbClr></a:lnRef><a:fillRef idx="1"><a:srgbClr val="0070A3"/></a:fillRef><a:effectRef idx="0"><a:scrgbClr r="0" g="0" b="0"/></a:effectRef><a:fontRef idx="none"/></wps:style><wps:bodyPr/></wps:wsp><wps:wsp><wps:cNvPr id="7" name="Rectangle 7"/><wps:cNvSpPr/><wps:spPr><a:xfrm><a:off x="5132807" y="554263"/><a:ext cx="2380347" cy="277118"/></a:xfrm><a:prstGeom prst="rect"><a:avLst/></a:prstGeom><a:ln><a:noFill/></a:ln></wps:spPr><wps:txbx><w:txbxContent><w:p w14:paraId="46A93935" w14:textId="77777777" w:rsidR="00EF5116" w:rsidRDefault="00000000"><w:pPr><w:spacing w:after="160" w:line="259" w:lineRule="auto"/><w:ind w:left="0" w:firstLine="0"/></w:pPr><w:r><w:rPr><w:color w:val="0070A3"/><w:w w:val="108"/><w:sz w:val="28"/></w:rPr><w:t>Terms</w:t></w:r><w:r><w:rPr><w:color w:val="0070A3"/><w:spacing w:val="5"/><w:w w:val="108"/><w:sz w:val="28"/></w:rPr><w:t xml:space="preserve"> </w:t></w:r><w:r><w:rPr><w:color w:val="0070A3"/><w:w w:val="108"/><w:sz w:val="28"/></w:rPr><w:t>&amp;</w:t></w:r><w:r><w:rPr><w:color w:val="0070A3"/><w:spacing w:val="5"/><w:w w:val="108"/><w:sz w:val="28"/></w:rPr><w:t xml:space="preserve"> </w:t></w:r><w:r><w:rPr><w:color w:val="0070A3"/><w:w w:val="108"/><w:sz w:val="28"/></w:rPr><w:t>Conditions</w:t></w:r><w:r><w:rPr><w:color w:val="0070A3"/><w:spacing w:val="5"/><w:w w:val="108"/><w:sz w:val="28"/></w:rPr><w:t xml:space="preserve"> </w:t></w:r><w:r><w:rPr><w:color w:val="0070A3"/><w:w w:val="108"/><w:sz w:val="28"/></w:rPr><w:t>for</w:t></w:r></w:p></w:txbxContent></wps:txbx><wps:bodyPr horzOverflow="overflow" vert="horz" lIns="0" tIns="0" rIns="0" bIns="0" rtlCol="0"><a:noAutofit/></wps:bodyPr></wps:wsp><wps:wsp><wps:cNvPr id="8" name="Rectangle 8"/><wps:cNvSpPr/><wps:spPr><a:xfrm><a:off x="5546141" y="732063"/><a:ext cx="1830664" cy="277118"/></a:xfrm><a:prstGeom prst="rect"><a:avLst/></a:prstGeom><a:ln><a:noFill/></a:ln></wps:spPr><wps:txbx><w:txbxContent><w:p w14:paraId="7B7BCA51" w14:textId="77777777" w:rsidR="00EF5116" w:rsidRDefault="00000000"><w:pPr><w:spacing w:after="160" w:line="259" w:lineRule="auto"/><w:ind w:left="0" w:firstLine="0"/></w:pPr><w:r><w:rPr><w:color w:val="0070A3"/><w:w w:val="109"/><w:sz w:val="28"/></w:rPr><w:t>the</w:t></w:r><w:r><w:rPr><w:color w:val="0070A3"/><w:spacing w:val="5"/><w:w w:val="109"/><w:sz w:val="28"/></w:rPr><w:t xml:space="preserve"> </w:t></w:r><w:r><w:rPr><w:color w:val="0070A3"/><w:w w:val="109"/><w:sz w:val="28"/></w:rPr><w:t>Sale</w:t></w:r><w:r><w:rPr><w:color w:val="0070A3"/><w:spacing w:val="5"/><w:w w:val="109"/><w:sz w:val="28"/></w:rPr><w:t xml:space="preserve"> </w:t></w:r><w:r><w:rPr><w:color w:val="0070A3"/><w:w w:val="109"/><w:sz w:val="28"/></w:rPr><w:t>of</w:t></w:r><w:r><w:rPr><w:color w:val="0070A3"/><w:spacing w:val="5"/><w:w w:val="109"/><w:sz w:val="28"/></w:rPr><w:t xml:space="preserve"> </w:t></w:r><w:r><w:rPr><w:color w:val="0070A3"/><w:w w:val="109"/><w:sz w:val="28"/></w:rPr><w:t>Goods</w:t></w:r></w:p></w:txbxContent></wps:txbx><wps:bodyPr horzOverflow="overflow" vert="horz" lIns="0" tIns="0" rIns="0" bIns="0" rtlCol="0"><a:noAutofit/></wps:bodyPr></wps:wsp><wps:wsp><wps:cNvPr id="10134" name="Shape 10134"/><wps:cNvSpPr/><wps:spPr><a:xfrm><a:off x="540000" y="540004"/><a:ext cx="1618809" cy="402869"/></a:xfrm><a:custGeom><a:avLst/><a:gdLst/><a:ahLst/><a:cxnLst/><a:rect l="0" t="0" r="0" b="0"/><a:pathLst><a:path w="1618809" h="402869"><a:moveTo><a:pt x="0" y="0"/></a:moveTo><a:lnTo><a:pt x="1618809" y="0"/></a:lnTo><a:lnTo><a:pt x="1618809" y="402869"/></a:lnTo><a:lnTo><a:pt x="0" y="402869"/></a:lnTo><a:lnTo><a:pt x="0" y="0"/></a:lnTo></a:path></a:pathLst></a:custGeom><a:ln w="0" cap="flat"><a:miter lim="127000"/></a:ln></wps:spPr><wps:style><a:lnRef idx="0"><a:srgbClr val="000000"><a:alpha val="0"/></a:srgbClr></a:lnRef><a:fillRef idx="1"><a:srgbClr val="000000"/></a:fillRef><a:effectRef idx="0"><a:scrgbClr r="0" g="0" b="0"/></a:effectRef><a:fontRef idx="none"/></wps:style><wps:bodyPr/></wps:wsp><wps:wsp><wps:cNvPr id="1146" name="Shape 1146"/><wps:cNvSpPr/><wps:spPr><a:xfrm><a:off x="3419121" y="594562"/><a:ext cx="326878" cy="300917"/></a:xfrm><a:custGeom><a:avLst/><a:gdLst/><a:ahLst/><a:cxnLst/><a:rect l="0" t="0" r="0" b="0"/><a:pathLst><a:path w="326878" h="300917"><a:moveTo><a:pt x="0" y="0"/></a:moveTo><a:lnTo><a:pt x="93217" y="0"/></a:lnTo><a:lnTo><a:pt x="93217" y="222834"/></a:lnTo><a:lnTo><a:pt x="326878" y="222834"/></a:lnTo><a:lnTo><a:pt x="266264" y="300917"/></a:lnTo><a:lnTo><a:pt x="0" y="300917"/></a:lnTo><a:lnTo><a:pt x="0" y="0"/></a:lnTo><a:close/></a:path></a:pathLst></a:custGeom><a:ln w="0" cap="flat"><a:miter lim="127000"/></a:ln></wps:spPr><wps:style><a:lnRef idx="0"><a:srgbClr val="000000"><a:alpha val="0"/></a:srgbClr></a:lnRef><a:fillRef idx="1"><a:srgbClr val="000000"/></a:fillRef><a:effectRef idx="0"><a:scrgbClr r="0" g="0" b="0"/></a:effectRef><a:fontRef idx="none"/></wps:style><wps:bodyPr/></wps:wsp><wps:wsp><wps:cNvPr id="1147" name="Shape 1147"/><wps:cNvSpPr/><wps:spPr><a:xfrm><a:off x="3073015" y="594562"/><a:ext cx="326878" cy="300917"/></a:xfrm><a:custGeom><a:avLst/><a:gdLst/><a:ahLst/><a:cxnLst/><a:rect l="0" t="0" r="0" b="0"/><a:pathLst><a:path w="326878" h="300917"><a:moveTo><a:pt x="0" y="0"/></a:moveTo><a:lnTo><a:pt x="93217" y="0"/></a:lnTo><a:lnTo><a:pt x="93217" y="222834"/></a:lnTo><a:lnTo><a:pt x="326878" y="222834"/></a:lnTo><a:lnTo><a:pt x="266263" y="300917"/></a:lnTo><a:lnTo><a:pt x="0" y="300917"/></a:lnTo><a:lnTo><a:pt x="0" y="0"/></a:lnTo><a:close/></a:path></a:pathLst></a:custGeom><a:ln w="0" cap="flat"><a:miter lim="127000"/></a:ln></wps:spPr><wps:style><a:lnRef idx="0"><a:srgbClr val="000000"><a:alpha val="0"/></a:srgbClr></a:lnRef><a:fillRef idx="1"><a:srgbClr val="000000"/></a:fillRef><a:effectRef idx="0"><a:scrgbClr r="0" g="0" b="0"/></a:effectRef><a:fontRef idx="none"/></wps:style><wps:bodyPr/></wps:wsp><wps:wsp><wps:cNvPr id="1148" name="Shape 1148"/><wps:cNvSpPr/><wps:spPr><a:xfrm><a:off x="2189452" y="594562"/><a:ext cx="393335" cy="300917"/></a:xfrm><a:custGeom><a:avLst/><a:gdLst/><a:ahLst/><a:cxnLst/><a:rect l="0" t="0" r="0" b="0"/><a:pathLst><a:path w="393335" h="300917"><a:moveTo><a:pt x="181830" y="0"/></a:moveTo><a:lnTo><a:pt x="393335" y="0"/></a:lnTo><a:lnTo><a:pt x="333142" y="78168"/></a:lnTo><a:lnTo><a:pt x="181830" y="78168"/></a:lnTo><a:cubicBezTo><a:pt x="156323" y="78168"/><a:pt x="135011" y="85239"/><a:pt x="118288" y="98533"/></a:cubicBezTo><a:cubicBezTo><a:pt x="101578" y="112254"/><a:pt x="93217" y="130134"/><a:pt x="93217" y="151332"/></a:cubicBezTo><a:cubicBezTo><a:pt x="93217" y="172532"/><a:pt x="101578" y="189578"/><a:pt x="118288" y="202883"/></a:cubicBezTo><a:cubicBezTo><a:pt x="135011" y="216178"/><a:pt x="156323" y="222834"/><a:pt x="181830" y="222834"/></a:cubicBezTo><a:lnTo><a:pt x="393335" y="222834"/></a:lnTo><a:lnTo><a:pt x="333142" y="300917"/></a:lnTo><a:lnTo><a:pt x="181830" y="300917"/></a:lnTo><a:cubicBezTo><a:pt x="129577" y="300917"/><a:pt x="86108" y="286227"/><a:pt x="51831" y="257260"/></a:cubicBezTo><a:cubicBezTo><a:pt x="17145" y="227873"/><a:pt x="0" y="191239"/><a:pt x="0" y="147587"/></a:cubicBezTo><a:cubicBezTo><a:pt x="0" y="103946"/><a:pt x="17145" y="68137"/><a:pt x="51000" y="40969"/></a:cubicBezTo><a:cubicBezTo><a:pt x="84855" y="13794"/><a:pt x="128747" y="0"/><a:pt x="181830" y="0"/></a:cubicBezTo><a:close/></a:path></a:pathLst></a:custGeom><a:ln w="0" cap="flat"><a:miter lim="127000"/></a:ln></wps:spPr><wps:style><a:lnRef idx="0"><a:srgbClr val="000000"><a:alpha val="0"/></a:srgbClr></a:lnRef><a:fillRef idx="1"><a:srgbClr val="000000"/></a:fillRef><a:effectRef idx="0"><a:scrgbClr r="0" g="0" b="0"/></a:effectRef><a:fontRef idx="none"/></wps:style><wps:bodyPr/></wps:wsp><wps:wsp><wps:cNvPr id="1149" name="Shape 1149"/><wps:cNvSpPr/><wps:spPr><a:xfrm><a:off x="2553657" y="593728"/><a:ext cx="501599" cy="301791"/></a:xfrm><a:custGeom><a:avLst/><a:gdLst/><a:ahLst/><a:cxnLst/><a:rect l="0" t="0" r="0" b="0"/><a:pathLst><a:path w="501599" h="301791"><a:moveTo><a:pt x="253312" y="0"/></a:moveTo><a:cubicBezTo><a:pt x="264588" y="0"/><a:pt x="276300" y="3756"/><a:pt x="287998" y="10848"/></a:cubicBezTo><a:cubicBezTo><a:pt x="298443" y="17102"/><a:pt x="306805" y="25034"/><a:pt x="313083" y="34210"/></a:cubicBezTo><a:lnTo><a:pt x="501599" y="301791"/></a:lnTo><a:lnTo><a:pt x="147553" y="301791"/></a:lnTo><a:lnTo><a:pt x="203974" y="223628"/></a:lnTo><a:lnTo><a:pt x="329792" y="223628"/></a:lnTo><a:lnTo><a:pt x="251624" y="115567"/></a:lnTo><a:lnTo><a:pt x="115782" y="301791"/></a:lnTo><a:lnTo><a:pt x="0" y="301791"/></a:lnTo><a:lnTo><a:pt x="193106" y="34210"/></a:lnTo><a:cubicBezTo><a:pt x="199384" y="25448"/><a:pt x="207746" y="17528"/><a:pt x="218613" y="10848"/></a:cubicBezTo><a:cubicBezTo><a:pt x="230733" y="3756"/><a:pt x="242023" y="0"/><a:pt x="253312" y="0"/></a:cubicBezTo><a:close/></a:path></a:pathLst></a:custGeom><a:ln w="0" cap="flat"><a:miter lim="127000"/></a:ln></wps:spPr><wps:style><a:lnRef idx="0"><a:srgbClr val="000000"><a:alpha val="0"/></a:srgbClr></a:lnRef><a:fillRef idx="1"><a:srgbClr val="000000"/></a:fillRef><a:effectRef idx="0"><a:scrgbClr r="0" g="0" b="0"/></a:effectRef><a:fontRef idx="none"/></wps:style><wps:bodyPr/></wps:wsp><wps:wsp><wps:cNvPr id="1150" name="Shape 1150"/><wps:cNvSpPr/><wps:spPr><a:xfrm><a:off x="1755823" y="592048"/><a:ext cx="373695" cy="300918"/></a:xfrm><a:custGeom><a:avLst/><a:gdLst/><a:ahLst/><a:cxnLst/><a:rect l="0" t="0" r="0" b="0"/><a:pathLst><a:path w="373695" h="300918"><a:moveTo><a:pt x="0" y="0"/></a:moveTo><a:lnTo><a:pt x="251226" y="0"/></a:lnTo><a:cubicBezTo><a:pt x="285081" y="0"/><a:pt x="313502" y="7950"/><a:pt x="336490" y="23407"/></a:cubicBezTo><a:cubicBezTo><a:pt x="361152" y="40134"/><a:pt x="373273" y="62282"/><a:pt x="373273" y="90097"/></a:cubicBezTo><a:cubicBezTo><a:pt x="373273" y="117571"/><a:pt x="361152" y="139814"/><a:pt x="336490" y="156609"/></a:cubicBezTo><a:cubicBezTo><a:pt x="313502" y="172146"/><a:pt x="285081" y="180119"/><a:pt x="251226" y="180119"/></a:cubicBezTo><a:lnTo><a:pt x="133765" y="180119"/></a:lnTo><a:cubicBezTo><a:pt x="124987" y="180119"/><a:pt x="116628" y="181350"/><a:pt x="108684" y="183819"/></a:cubicBezTo><a:cubicBezTo><a:pt x="97818" y="187512"/><a:pt x="92382" y="192852"/><a:pt x="92382" y="199836"/></a:cubicBezTo><a:lnTo><a:pt x="92382" y="222834"/></a:lnTo><a:lnTo><a:pt x="373695" y="222834"/></a:lnTo><a:lnTo><a:pt x="313502" y="300918"/></a:lnTo><a:lnTo><a:pt x="4188" y="300918"/></a:lnTo><a:lnTo><a:pt x="4188" y="199836"/></a:lnTo><a:cubicBezTo><a:pt x="4188" y="170887"/><a:pt x="17141" y="146953"/><a:pt x="43476" y="128063"/></a:cubicBezTo><a:cubicBezTo><a:pt x="68141" y="110852"/><a:pt x="98232" y="102029"/><a:pt x="133765" y="102029"/></a:cubicBezTo><a:lnTo><a:pt x="251226" y="102029"/></a:lnTo><a:cubicBezTo><a:pt x="262502" y="102029"/><a:pt x="268358" y="97915"/><a:pt x="268358" y="90097"/></a:cubicBezTo><a:cubicBezTo><a:pt x="268358" y="82283"/><a:pt x="262502" y="78175"/><a:pt x="251226" y="78175"/></a:cubicBezTo><a:lnTo><a:pt x="60198" y="78175"/></a:lnTo><a:lnTo><a:pt x="0" y="0"/></a:lnTo><a:close/></a:path></a:pathLst></a:custGeom><a:ln w="0" cap="flat"><a:miter lim="127000"/></a:ln></wps:spPr><wps:style><a:lnRef idx="0"><a:srgbClr val="000000"><a:alpha val="0"/></a:srgbClr></a:lnRef><a:fillRef idx="1"><a:srgbClr val="0077AB"/></a:fillRef><a:effectRef idx="0"><a:scrgbClr r="0" g="0" b="0"/></a:effectRef><a:fontRef idx="none"/></wps:style><wps:bodyPr/></wps:wsp><wps:wsp><wps:cNvPr id="1151" name="Shape 1151"/><wps:cNvSpPr/><wps:spPr><a:xfrm><a:off x="570284" y="592048"/><a:ext cx="220402" cy="300918"/></a:xfrm><a:custGeom><a:avLst/><a:gdLst/><a:ahLst/><a:cxnLst/><a:rect l="0" t="0" r="0" b="0"/><a:pathLst><a:path w="220402" h="300918"><a:moveTo><a:pt x="182240" y="0"/></a:moveTo><a:lnTo><a:pt x="220402" y="0"/></a:lnTo><a:lnTo><a:pt x="220402" y="78175"/></a:lnTo><a:lnTo><a:pt x="182240" y="78175"/></a:lnTo><a:cubicBezTo><a:pt x="156326" y="78175"/><a:pt x="135013" y="84820"/><a:pt x="118291" y="98535"/></a:cubicBezTo><a:cubicBezTo><a:pt x="101575" y="112255"/><a:pt x="93211" y="130134"/><a:pt x="93211" y="151332"/></a:cubicBezTo><a:cubicBezTo><a:pt x="93211" y="172532"/><a:pt x="101575" y="189992"/><a:pt x="118291" y="202884"/></a:cubicBezTo><a:cubicBezTo><a:pt x="135013" y="216178"/><a:pt x="156326" y="222834"/><a:pt x="182240" y="222834"/></a:cubicBezTo><a:lnTo><a:pt x="220402" y="222834"/></a:lnTo><a:lnTo><a:pt x="220402" y="300918"/></a:lnTo><a:lnTo><a:pt x="182240" y="300918"/></a:lnTo><a:cubicBezTo><a:pt x="129578" y="300918"/><a:pt x="86107" y="286227"/><a:pt x="51829" y="257260"/></a:cubicBezTo><a:cubicBezTo><a:pt x="17136" y="227873"/><a:pt x="0" y="191241"/><a:pt x="0" y="147587"/></a:cubicBezTo><a:cubicBezTo><a:pt x="0" y="103948"/><a:pt x="17136" y="68137"/><a:pt x="50995" y="40969"/></a:cubicBezTo><a:cubicBezTo><a:pt x="85273" y="13795"/><a:pt x="129157" y="0"/><a:pt x="182240" y="0"/></a:cubicBezTo><a:close/></a:path></a:pathLst></a:custGeom><a:ln w="0" cap="flat"><a:miter lim="127000"/></a:ln></wps:spPr><wps:style><a:lnRef idx="0"><a:srgbClr val="000000"><a:alpha val="0"/></a:srgbClr></a:lnRef><a:fillRef idx="1"><a:srgbClr val="FFFFFF"/></a:fillRef><a:effectRef idx="0"><a:scrgbClr r="0" g="0" b="0"/></a:effectRef><a:fontRef idx="none"/></wps:style><wps:bodyPr/></wps:wsp><wps:wsp><wps:cNvPr id="1152" name="Shape 1152"/><wps:cNvSpPr/><wps:spPr><a:xfrm><a:off x="1411940" y="592048"/><a:ext cx="327285" cy="300918"/></a:xfrm><a:custGeom><a:avLst/><a:gdLst/><a:ahLst/><a:cxnLst/><a:rect l="0" t="0" r="0" b="0"/><a:pathLst><a:path w="327285" h="300918"><a:moveTo><a:pt x="0" y="0"/></a:moveTo><a:lnTo><a:pt x="327285" y="0"/></a:lnTo><a:lnTo><a:pt x="267093" y="78175"/></a:lnTo><a:lnTo><a:pt x="93625" y="78175"/></a:lnTo><a:lnTo><a:pt x="93625" y="109558"/></a:lnTo><a:lnTo><a:pt x="312656" y="109558"/></a:lnTo><a:lnTo><a:pt x="252458" y="187643"/></a:lnTo><a:lnTo><a:pt x="93625" y="187643"/></a:lnTo><a:lnTo><a:pt x="93625" y="222834"/></a:lnTo><a:lnTo><a:pt x="327285" y="222834"/></a:lnTo><a:lnTo><a:pt x="267093" y="300918"/></a:lnTo><a:lnTo><a:pt x="0" y="300918"/></a:lnTo><a:lnTo><a:pt x="0" y="0"/></a:lnTo><a:close/></a:path></a:pathLst></a:custGeom><a:ln w="0" cap="flat"><a:miter lim="127000"/></a:ln></wps:spPr><wps:style><a:lnRef idx="0"><a:srgbClr val="000000"><a:alpha val="0"/></a:srgbClr></a:lnRef><a:fillRef idx="1"><a:srgbClr val="FFFFFF"/></a:fillRef><a:effectRef idx="0"><a:scrgbClr r="0" g="0" b="0"/></a:effectRef><a:fontRef idx="none"/></wps:style><wps:bodyPr/></wps:wsp><wps:wsp><wps:cNvPr id="1153" name="Shape 1153"/><wps:cNvSpPr/><wps:spPr><a:xfrm><a:off x="1033082" y="592048"/><a:ext cx="358222" cy="303471"/></a:xfrm><a:custGeom><a:avLst/><a:gdLst/><a:ahLst/><a:cxnLst/><a:rect l="0" t="0" r="0" b="0"/><a:pathLst><a:path w="358222" h="303471"><a:moveTo><a:pt x="264591" y="0"/></a:moveTo><a:lnTo><a:pt x="358222" y="0"/></a:lnTo><a:lnTo><a:pt x="358222" y="262508"/></a:lnTo><a:cubicBezTo><a:pt x="358222" y="289677"/><a:pt x="345682" y="303471"/><a:pt x="321021" y="303471"/></a:cubicBezTo><a:cubicBezTo><a:pt x="303045" y="303471"/><a:pt x="285909" y="296781"/><a:pt x="270026" y="283407"/></a:cubicBezTo><a:lnTo><a:pt x="93631" y="135854"/></a:lnTo><a:lnTo><a:pt x="93631" y="301377"/></a:lnTo><a:lnTo><a:pt x="0" y="301377"/></a:lnTo><a:lnTo><a:pt x="0" y="38875"/></a:lnTo><a:cubicBezTo><a:pt x="0" y="27595"/><a:pt x="3342" y="18397"/><a:pt x="10447" y="11292"/></a:cubicBezTo><a:cubicBezTo><a:pt x="17557" y="4182"/><a:pt x="28003" y="421"/><a:pt x="40962" y="421"/></a:cubicBezTo><a:cubicBezTo><a:pt x="58099" y="421"/><a:pt x="73567" y="6271"/><a:pt x="88201" y="18397"/></a:cubicBezTo><a:lnTo><a:pt x="264591" y="165945"/></a:lnTo><a:lnTo><a:pt x="264591" y="0"/></a:lnTo><a:close/></a:path></a:pathLst></a:custGeom><a:ln w="0" cap="flat"><a:miter lim="127000"/></a:ln></wps:spPr><wps:style><a:lnRef idx="0"><a:srgbClr val="000000"><a:alpha val="0"/></a:srgbClr></a:lnRef><a:fillRef idx="1"><a:srgbClr val="FFFFFF"/></a:fillRef><a:effectRef idx="0"><a:scrgbClr r="0" g="0" b="0"/></a:effectRef><a:fontRef idx="none"/></wps:style><wps:bodyPr/></wps:wsp><wps:wsp><wps:cNvPr id="1154" name="Shape 1154"/><wps:cNvSpPr/><wps:spPr><a:xfrm><a:off x="790686" y="592048"/><a:ext cx="219988" cy="300918"/></a:xfrm><a:custGeom><a:avLst/><a:gdLst/><a:ahLst/><a:cxnLst/><a:rect l="0" t="0" r="0" b="0"/><a:pathLst><a:path w="219988" h="300918"><a:moveTo><a:pt x="0" y="0"/></a:moveTo><a:lnTo><a:pt x="38157" y="0"/></a:lnTo><a:cubicBezTo><a:pt x="91245" y="0"/><a:pt x="135129" y="13795"/><a:pt x="168988" y="40969"/></a:cubicBezTo><a:cubicBezTo><a:pt x="202846" y="68137"/><a:pt x="219988" y="103948"/><a:pt x="219988" y="147587"/></a:cubicBezTo><a:cubicBezTo><a:pt x="219988" y="191241"/><a:pt x="202846" y="227873"/><a:pt x="168574" y="256840"/></a:cubicBezTo><a:cubicBezTo><a:pt x="133876" y="286227"/><a:pt x="90411" y="300918"/><a:pt x="38157" y="300918"/></a:cubicBezTo><a:lnTo><a:pt x="0" y="300918"/></a:lnTo><a:lnTo><a:pt x="0" y="222834"/></a:lnTo><a:lnTo><a:pt x="38157" y="222834"/></a:lnTo><a:cubicBezTo><a:pt x="64076" y="222834"/><a:pt x="85389" y="216178"/><a:pt x="102111" y="203298"/></a:cubicBezTo><a:cubicBezTo><a:pt x="118828" y="189992"/><a:pt x="127191" y="172532"/><a:pt x="127191" y="151332"/></a:cubicBezTo><a:cubicBezTo><a:pt x="127191" y="130134"/><a:pt x="118828" y="112669"/><a:pt x="102111" y="98949"/></a:cubicBezTo><a:cubicBezTo><a:pt x="84975" y="85239"/><a:pt x="63651" y="78175"/><a:pt x="38157" y="78175"/></a:cubicBezTo><a:lnTo><a:pt x="0" y="78175"/></a:lnTo><a:lnTo><a:pt x="0" y="0"/></a:lnTo><a:close/></a:path></a:pathLst></a:custGeom><a:ln w="0" cap="flat"><a:miter lim="127000"/></a:ln></wps:spPr><wps:style><a:lnRef idx="0"><a:srgbClr val="000000"><a:alpha val="0"/></a:srgbClr></a:lnRef><a:fillRef idx="1"><a:srgbClr val="FFFFFF"/></a:fillRef><a:effectRef idx="0"><a:scrgbClr r="0" g="0" b="0"/></a:effectRef><a:fontRef idx="none"/></wps:style><wps:bodyPr/></wps:wsp><wps:wsp><wps:cNvPr id="10135" name="Shape 10135"/><wps:cNvSpPr/><wps:spPr><a:xfrm><a:off x="7020001" y="540001"/><a:ext cx="35999" cy="402872"/></a:xfrm><a:custGeom><a:avLst/><a:gdLst/><a:ahLst/><a:cxnLst/><a:rect l="0" t="0" r="0" b="0"/><a:pathLst><a:path w="35999" h="402872"><a:moveTo><a:pt x="0" y="0"/></a:moveTo><a:lnTo><a:pt x="35999" y="0"/></a:lnTo><a:lnTo><a:pt x="35999" y="402872"/></a:lnTo><a:lnTo><a:pt x="0" y="402872"/></a:lnTo><a:lnTo><a:pt x="0" y="0"/></a:lnTo></a:path></a:pathLst></a:custGeom><a:ln w="0" cap="flat"><a:miter lim="127000"/></a:ln></wps:spPr><wps:style><a:lnRef idx="0"><a:srgbClr val="000000"><a:alpha val="0"/></a:srgbClr></a:lnRef><a:fillRef idx="1"><a:srgbClr val="0070A3"/></a:fillRef><a:effectRef idx="0"><a:scrgbClr r="0" g="0" b="0"/></a:effectRef><a:fontRef idx="none"/></wps:style><wps:bodyPr/></wps:wsp></wpg:wgp></a:graphicData></a:graphic></wp:anchor></w:drawing></mc:Choice><mc:Fallback><w:pict><v:group w14:anchorId="5CE3A52A" id="Group 9109" o:spid="_x0000_s1026" style="position:absolute;left:0;text-align:left;margin-left:0;margin-top:0;width:595.3pt;height:74.25pt;z-index:251658240;mso-position-horizontal-relative:page;mso-position-vertical-relative:page" coordsize="75600,9428" o:gfxdata="UEsDBBQABgAIAAAAIQC2gziS/gAAAOEBAAATAAAAW0NvbnRlbnRfVHlwZXNdLnhtbJSRQU7DMBBF&#xA;90jcwfIWJU67QAgl6YK0S0CoHGBkTxKLZGx5TGhvj5O2G0SRWNoz/78nu9wcxkFMGNg6quQqL6RA&#xA;0s5Y6ir5vt9lD1JwBDIwOMJKHpHlpr69KfdHjyxSmriSfYz+USnWPY7AufNIadK6MEJMx9ApD/oD&#xA;OlTrorhX2lFEilmcO2RdNtjC5xDF9pCuTyYBB5bi6bQ4syoJ3g9WQ0ymaiLzg5KdCXlKLjvcW893&#xA;SUOqXwnz5DrgnHtJTxOsQfEKIT7DmDSUCaxw7Rqn8787ZsmRM9e2VmPeBN4uqYvTtW7jvijg9N/y&#xA;JsXecLq0q+WD6m8AAAD//wMAUEsDBBQABgAIAAAAIQA4/SH/1gAAAJQBAAALAAAAX3JlbHMvLnJl&#xA;bHOkkMFqwzAMhu+DvYPRfXGawxijTi+j0GvpHsDYimMaW0Yy2fr2M4PBMnrbUb/Q94l/f/hMi1qR&#xA;JVI2sOt6UJgd+ZiDgffL8ekFlFSbvV0oo4EbChzGx4f9GRdb25HMsYhqlCwG5lrLq9biZkxWOiqY&#xA;22YiTra2kYMu1l1tQD30/bPm3wwYN0x18gb45AdQl1tp5j/sFB2T0FQ7R0nTNEV3j6o9feQzro1i&#xA;OWA14Fm+Q8a1a8+Bvu/d/dMb2JY5uiPbhG/ktn4cqGU/er3pcvwCAAD//wMAUEsDBBQABgAIAAAA&#xA;IQCNJlnt+gwAAN1KAAAOAAAAZHJzL2Uyb0RvYy54bWzsXG1vGzcS/n7A/QdB3y9ekvtCGnGKtL0U&#xA;BxyuRdv7AWtZsgVIWmGlxE5//T3kcLjkamWtcq0T2M6H7Eokh8PhzDMvpPz2u4f1avJp3u6WzeZq&#xA;Kt5k08l8M2tulpvbq+l/f//wDz2d7Pb15qZeNZv51fTzfDf97t3f//b2fns5l81ds7qZtxMQ2ewu&#xA;77dX07v9fnt5cbGb3c3X9e5Ns51v0Lho2nW9x8f29uKmre9Bfb26kFlWXtw37c22bWbz3Q7f/kiN&#xA;03eO/mIxn+1/Xix28/1kdTUFb3v3f+v+v7b/X7x7W1/etvX2bjnzbNRfwMW6Xm4waSD1Y72vJx/b&#xA;5QGp9XLWNrtmsX8za9YXzWKxnM3dGrAakfVW81PbfNy6tdxe3t9ug5gg2p6cvpjs7D+ffmq3v21/&#xA;aSGJ++0tZOE+2bU8LNq1fYLLyYMT2ecgsvnDfjLDl1VRZllWTCcztJlc6kqRTGd3EPzBsNndPx8f&#xA;eMHTXiTM3G+hHrtOArv/TwK/3dXbuRPs7hIS+KWdLG+gvZkQ1XSyqddQVNdlQl850bieQVC7yx1k&#xA;9kVSkgIik1ZKYbH15ezjbv/TvHHyrj/9e7cnxbzht/qO32YPG35tod6PKva23ttxlk37OrmPNuzu&#xA;auo5sc3r5tP898Z13Pd2DVx2ratN3CvsPisG+nIPfm4dvbhnIgDuxk/qDlMFydEdnR2HufFiV+vk&#xA;GySAL2MZrzZWGJhmVgN1Fqt678x3vdwDjlbLNbRBVtBsv02rDahZJaRdd2/7z6u5Fdhq8+t8AQVy&#xA;JmK/2LW31z+s2smn2oKO++eI16vtXe2/9XR9V8eqo2PHL5arVSAp3NAeySp778wMi/Kd7bi5w7sw&#xA;MqORM88NgR6gA4tm6MP4MMjN3Gz2YfwGgO3YjFZrX6+bm88OLpxAYJUWOJ7APINp/gq1rze3q/mk&#xA;svzZyWHEp02zEErqDGSgWkWRy9JDFWOZVDpTOdotlsmqEkL7bWIk3LZkpRP7cjW19kc76y3Wap7v&#xA;YsVptaa+3DQfsKFk7gN6tH+4fvCrIMlO7pr2j5/hUxerBjoKw3RvU+tmMaltnU5W/9oAA61H45eW&#xA;X675pd2vfmic3yM23n/cN4ulRRa3czSb//B024iAgBC220Yn5vHbWOSlyIXbxkrJrL+NQqusLPOv&#xA;sI3kRVgnX8RuwkEqiLrnM/HVWYaZW5Aku7SvbjSgyYcKohRaZ4Y2NM+kLk3PLmNk/0u9Z2AF3tNz&#xA;Ym2r84+x+2Ln0bWmTi4QO+k9456JAJggP+PpR3dkPomIxbDn7T2dshEevxzvKURe9uzUfnOOmapc&#xA;GCEJeAuTF6ULYjs7VbLUFeDduk+VZQbBNEmZ3eeTmSlzAiv1jHy5lRolbVZw0ka7flJKTQgIW2LL&#xA;5CdZKDNoA43TvWVZSuvQ+nJlmvyMrT/ZAO7Az7hjav2IklfNbk779ooDNsSyqrN7NlE0cCAE0j7H&#xA;td+chQNZpTKBnB/6+IoDnYmTVf3VOKBecYByrj8tm36p8UDIxAIOnJeISaERBcjjOGCUUr40mLij&#xA;p48HPCePxwNC29TRLYed4rHQXXmCJ6MCSEDkJKJKi5ILCuyI+UnQETEw1Hn28Xo5+37+R1yBE0Wp&#xA;JEFCGIIA3tXchCpQ0XTr0YVULmkKbUJLDQXAAowuFFeT0inST54okN8GeRgohJSFz9X62CfgISgG&#xA;4hk7XBQoxCgugKZzpJ8OiFayoIFMFOln4EYb+wpHFhq7NUpkjfqMRXaSQw1S9Mh2Iu9itzBnp0Nd&#xA;I8LAdGHptkfKlIzhXvwkcUQalRgV9+Kn366On8HeKV9+jIQkKeTtxvACdSky2n7k4VK6yIHbCtgP&#xA;6ZssKlmyEaVzpJ/8jJXIKZ4AxXCEQG1kkDbzSDXYf59XheY8IyWdfkqIZcpQ7sOci8BAqYXqLYpr&#xA;E3lmQuUhJZ5+oql0rgtaEwiaxEwEjklsFMboEbjoNuuI7F5jc5RcQ4X6GcbmqHIltTSRO9geXRyV&#xA;RaHKgnSrMKqSHhG5lgaPUBhfSgNEV0Z8rRydOXE+2TEylKMD8JUg/8km0fnkIbNDolx4x+YGsG3J&#xA;qgSYOZtTOIyK/QSs0Rjv0jKYrZdISj39RCYujc5zcr4AEDrT4/lQg9b2XBQ2LgscK8QTKnhHeCPb&#xA;pnIpeGHpFCmOs7TskHjbuBc/iTFkdNADmuB0bwk4rKi8IKUqSWUeKV2YytCOjOgtC1FKoi1EUZQM&#xA;1cwvPz3f1psT7RGr9Lt5eoHCKJGh+tWTN8+dyt1zYozSXiZFTjrBWyuzqrLFNJATVcEW5lVCwEF6&#xA;lThPlxSyar9lff3MEb5QU6rSh7aRLuW1lGMvgDxjd1HABFJ3gW/OKeVAfwvtdaswMmNFZ3ehKlWa&#xA;OIVjcHz6FM5zwimcdkWAzheQ+REkMKB2rWzq3kgLZC5kwNyVO6QG5LvrItMU1yb2BxgvAPoWBypD&#xA;gmeIUKrMDTEjVY4zZyqoptTTTzSXKgGTRDPvZ1DYDInrNXY+RN7AySjXidoMSu9nTNgRxe2XonLx&#xA;QFhGx41QRovUi3VrRBZa4oBu9CI7wYlK+mMInlN20hYa+WuStsKd8M51jSfSKySbVekj8UAwcm9D&#xA;2yBkbpBWOIgPY5hDIVCP9/ECsoV055Edld5xIBvSxP4Bh0NzGiTwTLXCOuPtNbibQFohDAR0tM1o&#xA;5UKbgwlZv0nLOnJjEk5veVC7Mb27vXXJIwMGM8BPYiTHya6T8jl9BaK1sEymNyTRQF1UmaYsMewh&#xA;Ej4yaaifQawU2VKOSyDeveO+CF0vOBDo0HzIHZko1KC3S4BZv4MZ3Hmi1bGGhsaDGXmlHpQiS4jH&#xA;cK8h/mSJUPQYEzi8UwVtBgI8lPcjicRtZ6FLNFDbc66UaOAGml+lE3arC20nBFJmwgfx8QgWBz9J&#xA;eKmb4LaXEy5V1fvv7VZApC/pBLyAxffCJefuRmfXRYU6ImUFQ9GSRABl7SscgDP4PXm0xJw8Hi2h&#xA;Pirz1BaOhkx+aXAC/ZCJzcfjUtfxtB1GDAx1HsIwV/AmdA5DAqjbsi0FSEjjZRKs4TKfRLHDenRb&#xA;8HZoc4AogxPaErMPH2zBO8EpW9T2bmSw4O3bzi94+4HDBW8OZoxBIh7BdLRGV/B24dq4RXaSO1Lw&#xA;JpF3AUCQeadDXePBnEd1JBnDvfh5oFEjooRIpQZ7D26xLXj34xBeoC14UyQ4WPCGJ7c6dX7BGxGM&#xA;G/hIwRvBRLS7ZKi2tPNlBW8HRrwq1Ks8A4cF78zYlA+LOrPgXXB2YgveiZkImJ4vSqZG2SkPo0q6&#xA;Py/FJX9w/16iS4a77LlkB2mjXTIibmG8ExvyyUiZkTB9Cz6ZOXncJ49zx0zrtDsuq8yQSwzuEujM&#xA;CMtPQlqD4i9Z/jl9RWZQRPK6ywT5SYRRwi9Rc7eYMqK3LCRq+NRbVyUq7BSqMk1+9pkW53Qe4Xgi&#xA;IY/oLTtJDzqelGva5tEdGR2ZyCsuPvfKLmy2h4vODMbjYqZwyETJ/iAuou4rQ66CisdXOwhE1cFx&#xA;4nDRMTJ4EIhzPR+/szEcy1WY4ElwjDq60kgfxNJYxEOZ5xbEpTYl7klEIZrCpehwfsUy5ZALqULm&#xA;b08r+zsjFng6S/rJz5mpzN+P6EYyWXg3Y38cYRkCPyhURwzZ37D5Sre9k3ykEM2oEgDV3+JAKU/T&#xA;BZ/HXIbvbPMfksbRzgx6YzuiZsd5GrM4JB4iK6siDToVzla9E8H5ZiwVkeX++gWuMFEKdZCxDE1k&#xA;T0soFUBlMcm8UCfMyMviPDeeyobQxIVvGDVRgZ+70Jb2yFXKHqHavS5lWqrXyHd90qj9cg+mYiHS&#xA;PtuTcm9RorT3eC3fR/cu6s32x+RendFzd0YoefWckSstjHZGlcFtCIr/hnyRtBV9BHzfQN3Mc/Kn&#xA;xOg6yXkjyxrCFtxv8xDvzIvRHRAMiCIYO8iqS+3EBjQ4L1O3xSF/geEg++e9AFFhr8klVYO48bw6&#xA;RDzSLjUByYifw/t/uDRb8O0UeFekegRTqRDTTwRwOFZBRkCe8eCuosmQOLq2LghnoePYzuN813YC&#xA;TNm14VdP/SiCYZKY8s7q9I9+OiYGk4+hBZdw8FxV4p8g8ZpQ89Q+Sji80Yq4xAsDd4Fwq2m8iHF+&#xA;F45CD8qRcFHsYA4LmVHjeeVR/DA/kD0ouqIEGhhC0kn3NVkGNv7y6zS4uj7+wFrnxpeADy5Sl7hu&#xA;R3oUcmaertvB0DRKi+LerDz8jJWILYHbXv3w8/bDCLBRnUkcsfsKeDjeE+OsOPOBYmF/a+2BOFz4&#xA;we1QwIT1xPb3w5WLcqG1T36CpYgROGLPx1BSSGDKdnA8H3RrwpK4J1sMP8mq/JT9pXMnfsYmmMiI&#xA;O/Az7pjODIE+899Wfmt/ocT9OSH8DSWX4fi/92T/SFP8Ge/xX6V69z8AAAD//wMAUEsDBBQABgAI&#xA;AAAAIQCQRYWw3QAAAAYBAAAPAAAAZHJzL2Rvd25yZXYueG1sTI9Ba8JAEIXvBf/DMoXe6ia2iqbZ&#xA;iEjbkwjVQvE2ZsckmJ0N2TWJ/75rL/YyvOEN732TLgdTi45aV1lWEI8jEMS51RUXCr73H89zEM4j&#xA;a6wtk4IrOVhmo4cUE217/qJu5wsRQtglqKD0vkmkdHlJBt3YNsTBO9nWoA9rW0jdYh/CTS0nUTST&#xA;BisODSU2tC4pP+8uRsFnj/3qJX7vNufT+nrYT7c/m5iUenocVm8gPA3+fgw3/IAOWWA62gtrJ2oF&#xA;4RH/N29evIhmII5Bvc6nILNU/sfPfgEAAP//AwBQSwECLQAUAAYACAAAACEAtoM4kv4AAADhAQAA&#xA;EwAAAAAAAAAAAAAAAAAAAAAAW0NvbnRlbnRfVHlwZXNdLnhtbFBLAQItABQABgAIAAAAIQA4/SH/&#xA;1gAAAJQBAAALAAAAAAAAAAAAAAAAAC8BAABfcmVscy8ucmVsc1BLAQItABQABgAIAAAAIQCNJlnt&#xA;+gwAAN1KAAAOAAAAAAAAAAAAAAAAAC4CAABkcnMvZTJvRG9jLnhtbFBLAQItABQABgAIAAAAIQCQ&#xA;RYWw3QAAAAYBAAAPAAAAAAAAAAAAAAAAAFQPAABkcnMvZG93bnJldi54bWxQSwUGAAAAAAQABADz&#xA;AAAAXhAAAAAA&#xA;"><v:shape id="Shape 10117" o:spid="_x0000_s1027" style="position:absolute;width:75600;height:2160;visibility:visible;mso-wrap-style:square;v-text-anchor:top" coordsize="7560005,216002" o:gfxdata="UEsDBBQABgAIAAAAIQDb4fbL7gAAAIUBAAATAAAAW0NvbnRlbnRfVHlwZXNdLnhtbHyQz07DMAyH&#xA;70i8Q+QralM4IITa7kDhCAiNB7ASt43WOlEcyvb2pNu4IODoPz9/n1xv9vOkForiPDdwXVagiI23&#xA;jocG3rdPxR0oScgWJ8/UwIEENu3lRb09BBKV0ywNjCmFe63FjDSjlD4Q50nv44wpl3HQAc0OB9I3&#xA;VXWrjedEnIq03oC27qjHjympx31un0wiTQLq4bS4shrAECZnMGVTvbD9QSnOhDInjzsyuiBXWQP0&#xA;r4R18jfgnHvJr4nOknrFmJ5xzhraRtHWf3Kkpfz/yGo5S+H73hkquyhdjr3R8m2lj09svwAAAP//&#xA;AwBQSwMEFAAGAAgAAAAhAFr0LFu/AAAAFQEAAAsAAABfcmVscy8ucmVsc2zPwWrDMAwG4Ptg72B0&#xA;X5TuUMaI01uh19I+gLGVxCy2jGSy9e1nemrHjpL4P0nD4SetZiPRyNnCruvBUPYcYp4tXC/Htw8w&#xA;Wl0ObuVMFm6kcBhfX4Yzra62kC6xqGlKVgtLreUTUf1CyWnHhXKbTCzJ1VbKjMX5LzcTvvf9HuXR&#xA;gPHJNKdgQU5hB+ZyK23zHztFL6w81c5zQp6m6P9TMfB3PtPWFCczVQtB9N4U2rp2HOA44NMz4y8A&#xA;AAD//wMAUEsDBBQABgAIAAAAIQCe/hn2wgAAAN4AAAAPAAAAZHJzL2Rvd25yZXYueG1sRE/NSgMx&#xA;EL4LvkMYwZvNbkFd1qZlEUQvIlYfYEymm62byZJM29WnN4LgbT6+31lt5jCqI6U8RDZQLypQxDa6&#xA;gXsD728PVw2oLMgOx8hk4IsybNbnZytsXTzxKx230qsSwrlFA15karXO1lPAvIgTceF2MQWUAlOv&#xA;XcJTCQ+jXlbVjQ44cGnwONG9J/u5PQQDL3L9Lf4jNbbpDsvn7lEGuxdjLi/m7g6U0Cz/4j/3kyvz&#xA;q7q+hd93yg16/QMAAP//AwBQSwECLQAUAAYACAAAACEA2+H2y+4AAACFAQAAEwAAAAAAAAAAAAAA&#xA;AAAAAAAAW0NvbnRlbnRfVHlwZXNdLnhtbFBLAQItABQABgAIAAAAIQBa9CxbvwAAABUBAAALAAAA&#xA;AAAAAAAAAAAAAB8BAABfcmVscy8ucmVsc1BLAQItABQABgAIAAAAIQCe/hn2wgAAAN4AAAAPAAAA&#xA;AAAAAAAAAAAAAAcCAABkcnMvZG93bnJldi54bWxQSwUGAAAAAAMAAwC3AAAA9gIAAAAA&#xA;" path="m,l7560005,r,216002l,216002,,e" fillcolor="#0070a3" stroked="f" strokeweight="0"><v:stroke miterlimit="83231f" joinstyle="miter"/><v:path arrowok="t" textboxrect="0,0,7560005,216002"/></v:shape><v:rect id="Rectangle 7" o:spid="_x0000_s1028" style="position:absolute;left:51328;top:5542;width:23803;height:2771;visibility:visible;mso-wrap-style:square;v-text-anchor:top" o:gfxdata="UEsDBBQABgAIAAAAIQDb4fbL7gAAAIUBAAATAAAAW0NvbnRlbnRfVHlwZXNdLnhtbHyQz07DMAyH&#xA;70i8Q+QralM4IITa7kDhCAiNB7ASt43WOlEcyvb2pNu4IODoPz9/n1xv9vOkForiPDdwXVagiI23&#xA;jocG3rdPxR0oScgWJ8/UwIEENu3lRb09BBKV0ywNjCmFe63FjDSjlD4Q50nv44wpl3HQAc0OB9I3&#xA;VXWrjedEnIq03oC27qjHjympx31un0wiTQLq4bS4shrAECZnMGVTvbD9QSnOhDInjzsyuiBXWQP0&#xA;r4R18jfgnHvJr4nOknrFmJ5xzhraRtHWf3Kkpfz/yGo5S+H73hkquyhdjr3R8m2lj09svwAAAP//&#xA;AwBQSwMEFAAGAAgAAAAhAFr0LFu/AAAAFQEAAAsAAABfcmVscy8ucmVsc2zPwWrDMAwG4Ptg72B0&#xA;X5TuUMaI01uh19I+gLGVxCy2jGSy9e1nemrHjpL4P0nD4SetZiPRyNnCruvBUPYcYp4tXC/Htw8w&#xA;Wl0ObuVMFm6kcBhfX4Yzra62kC6xqGlKVgtLreUTUf1CyWnHhXKbTCzJ1VbKjMX5LzcTvvf9HuXR&#xA;gPHJNKdgQU5hB+ZyK23zHztFL6w81c5zQp6m6P9TMfB3PtPWFCczVQtB9N4U2rp2HOA44NMz4y8A&#xA;AAD//wMAUEsDBBQABgAIAAAAIQC25a0uwwAAANoAAAAPAAAAZHJzL2Rvd25yZXYueG1sRI9Li8JA&#xA;EITvgv9haGFvOtGDq9FRxAd69AXqrcm0STDTEzKjye6vd4SFPRZV9RU1nTemEC+qXG5ZQb8XgSBO&#xA;rM45VXA+bbojEM4jaywsk4IfcjCftVtTjLWt+UCvo09FgLCLUUHmfRlL6ZKMDLqeLYmDd7eVQR9k&#xA;lUpdYR3gppCDKBpKgzmHhQxLWmaUPI5Po2A7KhfXnf2t02J92172l/HqNPZKfXWaxQSEp8b/h//a&#xA;O63gGz5Xwg2QszcAAAD//wMAUEsBAi0AFAAGAAgAAAAhANvh9svuAAAAhQEAABMAAAAAAAAAAAAA&#xA;AAAAAAAAAFtDb250ZW50X1R5cGVzXS54bWxQSwECLQAUAAYACAAAACEAWvQsW78AAAAVAQAACwAA&#xA;AAAAAAAAAAAAAAAfAQAAX3JlbHMvLnJlbHNQSwECLQAUAAYACAAAACEAtuWtLsMAAADaAAAADwAA&#xA;AAAAAAAAAAAAAAAHAgAAZHJzL2Rvd25yZXYueG1sUEsFBgAAAAADAAMAtwAAAPcCAAAAAA==&#xA;" filled="f" stroked="f"><v:textbox inset="0,0,0,0"><w:txbxContent><w:p w14:paraId="46A93935" w14:textId="77777777" w:rsidR="00EF5116" w:rsidRDefault="00000000"><w:pPr><w:spacing w:after="160" w:line="259" w:lineRule="auto"/><w:ind w:left="0" w:firstLine="0"/></w:pPr><w:r><w:rPr><w:color w:val="0070A3"/><w:w w:val="108"/><w:sz w:val="28"/></w:rPr><w:t>Terms</w:t></w:r><w:r><w:rPr><w:color w:val="0070A3"/><w:spacing w:val="5"/><w:w w:val="108"/><w:sz w:val="28"/></w:rPr><w:t xml:space="preserve"> </w:t></w:r><w:r><w:rPr><w:color w:val="0070A3"/><w:w w:val="108"/><w:sz w:val="28"/></w:rPr><w:t>&amp;</w:t></w:r><w:r><w:rPr><w:color w:val="0070A3"/><w:spacing w:val="5"/><w:w w:val="108"/><w:sz w:val="28"/></w:rPr><w:t xml:space="preserve"> </w:t></w:r><w:r><w:rPr><w:color w:val="0070A3"/><w:w w:val="108"/><w:sz w:val="28"/></w:rPr><w:t>Conditions</w:t></w:r><w:r><w:rPr><w:color w:val="0070A3"/><w:spacing w:val="5"/><w:w w:val="108"/><w:sz w:val="28"/></w:rPr><w:t xml:space="preserve"> </w:t></w:r><w:r><w:rPr><w:color w:val="0070A3"/><w:w w:val="108"/><w:sz w:val="28"/></w:rPr><w:t>for</w:t></w:r></w:p></w:txbxContent></v:textbox></v:rect><v:rect id="Rectangle 8" o:spid="_x0000_s1029" style="position:absolute;left:55461;top:7320;width:18307;height:2771;visibility:visible;mso-wrap-style:square;v-text-anchor:top" o:gfxdata="UEsDBBQABgAIAAAAIQDb4fbL7gAAAIUBAAATAAAAW0NvbnRlbnRfVHlwZXNdLnhtbHyQz07DMAyH&#xA;70i8Q+QralM4IITa7kDhCAiNB7ASt43WOlEcyvb2pNu4IODoPz9/n1xv9vOkForiPDdwXVagiI23&#xA;jocG3rdPxR0oScgWJ8/UwIEENu3lRb09BBKV0ywNjCmFe63FjDSjlD4Q50nv44wpl3HQAc0OB9I3&#xA;VXWrjedEnIq03oC27qjHjympx31un0wiTQLq4bS4shrAECZnMGVTvbD9QSnOhDInjzsyuiBXWQP0&#xA;r4R18jfgnHvJr4nOknrFmJ5xzhraRtHWf3Kkpfz/yGo5S+H73hkquyhdjr3R8m2lj09svwAAAP//&#xA;AwBQSwMEFAAGAAgAAAAhAFr0LFu/AAAAFQEAAAsAAABfcmVscy8ucmVsc2zPwWrDMAwG4Ptg72B0&#xA;X5TuUMaI01uh19I+gLGVxCy2jGSy9e1nemrHjpL4P0nD4SetZiPRyNnCruvBUPYcYp4tXC/Htw8w&#xA;Wl0ObuVMFm6kcBhfX4Yzra62kC6xqGlKVgtLreUTUf1CyWnHhXKbTCzJ1VbKjMX5LzcTvvf9HuXR&#xA;gPHJNKdgQU5hB+ZyK23zHztFL6w81c5zQp6m6P9TMfB3PtPWFCczVQtB9N4U2rp2HOA44NMz4y8A&#xA;AAD//wMAUEsDBBQABgAIAAAAIQDHejlcwAAAANoAAAAPAAAAZHJzL2Rvd25yZXYueG1sRE9Ni8Iw&#xA;EL0L/ocwgjdN3YNobSqiLnp07YLrbWjGtthMShNt9ddvDgt7fLzvZN2bWjypdZVlBbNpBII4t7ri&#xA;QsF39jlZgHAeWWNtmRS8yME6HQ4SjLXt+IueZ1+IEMIuRgWl900spctLMuimtiEO3M22Bn2AbSF1&#xA;i10IN7X8iKK5NFhxaCixoW1J+f38MAoOi2bzc7Tvrqj318PldFnusqVXajzqNysQnnr/L/5zH7WC&#xA;sDVcCTdApr8AAAD//wMAUEsBAi0AFAAGAAgAAAAhANvh9svuAAAAhQEAABMAAAAAAAAAAAAAAAAA&#xA;AAAAAFtDb250ZW50X1R5cGVzXS54bWxQSwECLQAUAAYACAAAACEAWvQsW78AAAAVAQAACwAAAAAA&#xA;AAAAAAAAAAAfAQAAX3JlbHMvLnJlbHNQSwECLQAUAAYACAAAACEAx3o5XMAAAADaAAAADwAAAAAA&#xA;AAAAAAAAAAAHAgAAZHJzL2Rvd25yZXYueG1sUEsFBgAAAAADAAMAtwAAAPQCAAAAAA==&#xA;" filled="f" stroked="f"><v:textbox inset="0,0,0,0"><w:txbxContent><w:p w14:paraId="7B7BCA51" w14:textId="77777777" w:rsidR="00EF5116" w:rsidRDefault="00000000"><w:pPr><w:spacing w:after="160" w:line="259" w:lineRule="auto"/><w:ind w:left="0" w:firstLine="0"/></w:pPr><w:r><w:rPr><w:color w:val="0070A3"/><w:w w:val="109"/><w:sz w:val="28"/></w:rPr><w:t>the</w:t></w:r><w:r><w:rPr><w:color w:val="0070A3"/><w:spacing w:val="5"/><w:w w:val="109"/><w:sz w:val="28"/></w:rPr><w:t xml:space="preserve"> </w:t></w:r><w:r><w:rPr><w:color w:val="0070A3"/><w:w w:val="109"/><w:sz w:val="28"/></w:rPr><w:t>Sale</w:t></w:r><w:r><w:rPr><w:color w:val="0070A3"/><w:spacing w:val="5"/><w:w w:val="109"/><w:sz w:val="28"/></w:rPr><w:t xml:space="preserve"> </w:t></w:r><w:r><w:rPr><w:color w:val="0070A3"/><w:w w:val="109"/><w:sz w:val="28"/></w:rPr><w:t>of</w:t></w:r><w:r><w:rPr><w:color w:val="0070A3"/><w:spacing w:val="5"/><w:w w:val="109"/><w:sz w:val="28"/></w:rPr><w:t xml:space="preserve"> </w:t></w:r><w:r><w:rPr><w:color w:val="0070A3"/><w:w w:val="109"/><w:sz w:val="28"/></w:rPr><w:t>Goods</w:t></w:r></w:p></w:txbxContent></v:textbox></v:rect><v:shape id="Shape 10134" o:spid="_x0000_s1030" style="position:absolute;left:5400;top:5400;width:16188;height:4028;visibility:visible;mso-wrap-style:square;v-text-anchor:top" coordsize="1618809,402869" o:gfxdata="UEsDBBQABgAIAAAAIQDb4fbL7gAAAIUBAAATAAAAW0NvbnRlbnRfVHlwZXNdLnhtbHyQz07DMAyH&#xA;70i8Q+QralM4IITa7kDhCAiNB7ASt43WOlEcyvb2pNu4IODoPz9/n1xv9vOkForiPDdwXVagiI23&#xA;jocG3rdPxR0oScgWJ8/UwIEENu3lRb09BBKV0ywNjCmFe63FjDSjlD4Q50nv44wpl3HQAc0OB9I3&#xA;VXWrjedEnIq03oC27qjHjympx31un0wiTQLq4bS4shrAECZnMGVTvbD9QSnOhDInjzsyuiBXWQP0&#xA;r4R18jfgnHvJr4nOknrFmJ5xzhraRtHWf3Kkpfz/yGo5S+H73hkquyhdjr3R8m2lj09svwAAAP//&#xA;AwBQSwMEFAAGAAgAAAAhAFr0LFu/AAAAFQEAAAsAAABfcmVscy8ucmVsc2zPwWrDMAwG4Ptg72B0&#xA;X5TuUMaI01uh19I+gLGVxCy2jGSy9e1nemrHjpL4P0nD4SetZiPRyNnCruvBUPYcYp4tXC/Htw8w&#xA;Wl0ObuVMFm6kcBhfX4Yzra62kC6xqGlKVgtLreUTUf1CyWnHhXKbTCzJ1VbKjMX5LzcTvvf9HuXR&#xA;gPHJNKdgQU5hB+ZyK23zHztFL6w81c5zQp6m6P9TMfB3PtPWFCczVQtB9N4U2rp2HOA44NMz4y8A&#xA;AAD//wMAUEsDBBQABgAIAAAAIQA/0wHVxQAAAN4AAAAPAAAAZHJzL2Rvd25yZXYueG1sRE9La8JA&#xA;EL4L/odlBG+68dFSUlcpRcFCCo3tIccxO01Cs7Nhd43pv+8WBG/z8T1nsxtMK3pyvrGsYDFPQBCX&#xA;VjdcKfj6PMyeQPiArLG1TAp+ycNuOx5tMNX2yjn1p1CJGMI+RQV1CF0qpS9rMujntiOO3Ld1BkOE&#xA;rpLa4TWGm1Yuk+RRGmw4NtTY0WtN5c/pYhTkH/vz2zpz+7J4x7w4V1nRP2RKTSfDyzOIQEO4i2/u&#xA;o47zk8VqDf/vxBvk9g8AAP//AwBQSwECLQAUAAYACAAAACEA2+H2y+4AAACFAQAAEwAAAAAAAAAA&#xA;AAAAAAAAAAAAW0NvbnRlbnRfVHlwZXNdLnhtbFBLAQItABQABgAIAAAAIQBa9CxbvwAAABUBAAAL&#xA;AAAAAAAAAAAAAAAAAB8BAABfcmVscy8ucmVsc1BLAQItABQABgAIAAAAIQA/0wHVxQAAAN4AAAAP&#xA;AAAAAAAAAAAAAAAAAAcCAABkcnMvZG93bnJldi54bWxQSwUGAAAAAAMAAwC3AAAA+QIAAAAA&#xA;" path="m,l1618809,r,402869l,402869,,e" fillcolor="black" stroked="f" strokeweight="0"><v:stroke miterlimit="83231f" joinstyle="miter"/><v:path arrowok="t" textboxrect="0,0,1618809,402869"/></v:shape><v:shape id="Shape 1146" o:spid="_x0000_s1031" style="position:absolute;left:34191;top:5945;width:3268;height:3009;visibility:visible;mso-wrap-style:square;v-text-anchor:top" coordsize="326878,300917" o:gfxdata="UEsDBBQABgAIAAAAIQDb4fbL7gAAAIUBAAATAAAAW0NvbnRlbnRfVHlwZXNdLnhtbHyQz07DMAyH&#xA;70i8Q+QralM4IITa7kDhCAiNB7ASt43WOlEcyvb2pNu4IODoPz9/n1xv9vOkForiPDdwXVagiI23&#xA;jocG3rdPxR0oScgWJ8/UwIEENu3lRb09BBKV0ywNjCmFe63FjDSjlD4Q50nv44wpl3HQAc0OB9I3&#xA;VXWrjedEnIq03oC27qjHjympx31un0wiTQLq4bS4shrAECZnMGVTvbD9QSnOhDInjzsyuiBXWQP0&#xA;r4R18jfgnHvJr4nOknrFmJ5xzhraRtHWf3Kkpfz/yGo5S+H73hkquyhdjr3R8m2lj09svwAAAP//&#xA;AwBQSwMEFAAGAAgAAAAhAFr0LFu/AAAAFQEAAAsAAABfcmVscy8ucmVsc2zPwWrDMAwG4Ptg72B0&#xA;X5TuUMaI01uh19I+gLGVxCy2jGSy9e1nemrHjpL4P0nD4SetZiPRyNnCruvBUPYcYp4tXC/Htw8w&#xA;Wl0ObuVMFm6kcBhfX4Yzra62kC6xqGlKVgtLreUTUf1CyWnHhXKbTCzJ1VbKjMX5LzcTvvf9HuXR&#xA;gPHJNKdgQU5hB+ZyK23zHztFL6w81c5zQp6m6P9TMfB3PtPWFCczVQtB9N4U2rp2HOA44NMz4y8A&#xA;AAD//wMAUEsDBBQABgAIAAAAIQA2I9gIwwAAAN0AAAAPAAAAZHJzL2Rvd25yZXYueG1sRE9Na8JA&#xA;EL0L/odlhN7qxlpEoquokNJbMUrQ25Adk2B2Nu5uNf333ULB2zze5yzXvWnFnZxvLCuYjBMQxKXV&#xA;DVcKjofsdQ7CB2SNrWVS8EMe1qvhYImptg/e0z0PlYgh7FNUUIfQpVL6siaDfmw74shdrDMYInSV&#xA;1A4fMdy08i1JZtJgw7Ghxo52NZXX/NsoOCfTr217mxb7j6ZwRb49ZZm2Sr2M+s0CRKA+PMX/7k8d&#xA;50/eZ/D3TTxBrn4BAAD//wMAUEsBAi0AFAAGAAgAAAAhANvh9svuAAAAhQEAABMAAAAAAAAAAAAA&#xA;AAAAAAAAAFtDb250ZW50X1R5cGVzXS54bWxQSwECLQAUAAYACAAAACEAWvQsW78AAAAVAQAACwAA&#xA;AAAAAAAAAAAAAAAfAQAAX3JlbHMvLnJlbHNQSwECLQAUAAYACAAAACEANiPYCMMAAADdAAAADwAA&#xA;AAAAAAAAAAAAAAAHAgAAZHJzL2Rvd25yZXYueG1sUEsFBgAAAAADAAMAtwAAAPcCAAAAAA==&#xA;" path="m,l93217,r,222834l326878,222834r-60614,78083l,300917,,xe" fillcolor="black" stroked="f" strokeweight="0"><v:stroke miterlimit="83231f" joinstyle="miter"/><v:path arrowok="t" textboxrect="0,0,326878,300917"/></v:shape><v:shape id="Shape 1147" o:spid="_x0000_s1032" style="position:absolute;left:30730;top:5945;width:3268;height:3009;visibility:visible;mso-wrap-style:square;v-text-anchor:top" coordsize="326878,300917" o:gfxdata="UEsDBBQABgAIAAAAIQDb4fbL7gAAAIUBAAATAAAAW0NvbnRlbnRfVHlwZXNdLnhtbHyQz07DMAyH&#xA;70i8Q+QralM4IITa7kDhCAiNB7ASt43WOlEcyvb2pNu4IODoPz9/n1xv9vOkForiPDdwXVagiI23&#xA;jocG3rdPxR0oScgWJ8/UwIEENu3lRb09BBKV0ywNjCmFe63FjDSjlD4Q50nv44wpl3HQAc0OB9I3&#xA;VXWrjedEnIq03oC27qjHjympx31un0wiTQLq4bS4shrAECZnMGVTvbD9QSnOhDInjzsyuiBXWQP0&#xA;r4R18jfgnHvJr4nOknrFmJ5xzhraRtHWf3Kkpfz/yGo5S+H73hkquyhdjr3R8m2lj09svwAAAP//&#xA;AwBQSwMEFAAGAAgAAAAhAFr0LFu/AAAAFQEAAAsAAABfcmVscy8ucmVsc2zPwWrDMAwG4Ptg72B0&#xA;X5TuUMaI01uh19I+gLGVxCy2jGSy9e1nemrHjpL4P0nD4SetZiPRyNnCruvBUPYcYp4tXC/Htw8w&#xA;Wl0ObuVMFm6kcBhfX4Yzra62kC6xqGlKVgtLreUTUf1CyWnHhXKbTCzJ1VbKjMX5LzcTvvf9HuXR&#xA;gPHJNKdgQU5hB+ZyK23zHztFL6w81c5zQp6m6P9TMfB3PtPWFCczVQtB9N4U2rp2HOA44NMz4y8A&#xA;AAD//wMAUEsDBBQABgAIAAAAIQBZb32TwwAAAN0AAAAPAAAAZHJzL2Rvd25yZXYueG1sRE9Na8JA&#xA;EL0X/A/LCL3VjVpaia6ihUhvxVSC3obsmASzs3F31fTfdwsFb/N4n7NY9aYVN3K+saxgPEpAEJdW&#xA;N1wp2H9nLzMQPiBrbC2Tgh/ysFoOnhaYanvnHd3yUIkYwj5FBXUIXSqlL2sy6Ee2I47cyTqDIUJX&#xA;Se3wHsNNKydJ8iYNNhwbauzoo6bynF+NgmMy/dq0l2mx2zaFK/LNIcu0Vep52K/nIAL14SH+d3/q&#xA;OH/8+g5/38QT5PIXAAD//wMAUEsBAi0AFAAGAAgAAAAhANvh9svuAAAAhQEAABMAAAAAAAAAAAAA&#xA;AAAAAAAAAFtDb250ZW50X1R5cGVzXS54bWxQSwECLQAUAAYACAAAACEAWvQsW78AAAAVAQAACwAA&#xA;AAAAAAAAAAAAAAAfAQAAX3JlbHMvLnJlbHNQSwECLQAUAAYACAAAACEAWW99k8MAAADdAAAADwAA&#xA;AAAAAAAAAAAAAAAHAgAAZHJzL2Rvd25yZXYueG1sUEsFBgAAAAADAAMAtwAAAPcCAAAAAA==&#xA;" path="m,l93217,r,222834l326878,222834r-60615,78083l,300917,,xe" fillcolor="black" stroked="f" strokeweight="0"><v:stroke miterlimit="83231f" joinstyle="miter"/><v:path arrowok="t" textboxrect="0,0,326878,300917"/></v:shape><v:shape id="Shape 1148" o:spid="_x0000_s1033" style="position:absolute;left:21894;top:5945;width:3933;height:3009;visibility:visible;mso-wrap-style:square;v-text-anchor:top" coordsize="393335,300917" o:gfxdata="UEsDBBQABgAIAAAAIQDb4fbL7gAAAIUBAAATAAAAW0NvbnRlbnRfVHlwZXNdLnhtbHyQz07DMAyH&#xA;70i8Q+QralM4IITa7kDhCAiNB7ASt43WOlEcyvb2pNu4IODoPz9/n1xv9vOkForiPDdwXVagiI23&#xA;jocG3rdPxR0oScgWJ8/UwIEENu3lRb09BBKV0ywNjCmFe63FjDSjlD4Q50nv44wpl3HQAc0OB9I3&#xA;VXWrjedEnIq03oC27qjHjympx31un0wiTQLq4bS4shrAECZnMGVTvbD9QSnOhDInjzsyuiBXWQP0&#xA;r4R18jfgnHvJr4nOknrFmJ5xzhraRtHWf3Kkpfz/yGo5S+H73hkquyhdjr3R8m2lj09svwAAAP//&#xA;AwBQSwMEFAAGAAgAAAAhAFr0LFu/AAAAFQEAAAsAAABfcmVscy8ucmVsc2zPwWrDMAwG4Ptg72B0&#xA;X5TuUMaI01uh19I+gLGVxCy2jGSy9e1nemrHjpL4P0nD4SetZiPRyNnCruvBUPYcYp4tXC/Htw8w&#xA;Wl0ObuVMFm6kcBhfX4Yzra62kC6xqGlKVgtLreUTUf1CyWnHhXKbTCzJ1VbKjMX5LzcTvvf9HuXR&#xA;gPHJNKdgQU5hB+ZyK23zHztFL6w81c5zQp6m6P9TMfB3PtPWFCczVQtB9N4U2rp2HOA44NMz4y8A&#xA;AAD//wMAUEsDBBQABgAIAAAAIQAyMdM6yAAAAN0AAAAPAAAAZHJzL2Rvd25yZXYueG1sRI9Ba8JA&#xA;EIXvBf/DMoKXohtrqRJdRYSCID3U1oO3MTtNUrOzIbuJsb++cyj0NsN78943q03vKtVRE0rPBqaT&#xA;BBRx5m3JuYHPj9fxAlSIyBYrz2TgTgE268HDClPrb/xO3THmSkI4pGigiLFOtQ5ZQQ7DxNfEon35&#xA;xmGUtcm1bfAm4a7ST0nyoh2WLA0F1rQrKLseW2eg7ZN2vv+Ojz+X60wfTm/n/NLVxoyG/XYJKlIf&#xA;/81/13sr+NNnwZVvZAS9/gUAAP//AwBQSwECLQAUAAYACAAAACEA2+H2y+4AAACFAQAAEwAAAAAA&#xA;AAAAAAAAAAAAAAAAW0NvbnRlbnRfVHlwZXNdLnhtbFBLAQItABQABgAIAAAAIQBa9CxbvwAAABUB&#xA;AAALAAAAAAAAAAAAAAAAAB8BAABfcmVscy8ucmVsc1BLAQItABQABgAIAAAAIQAyMdM6yAAAAN0A&#xA;AAAPAAAAAAAAAAAAAAAAAAcCAABkcnMvZG93bnJldi54bWxQSwUGAAAAAAMAAwC3AAAA/AIAAAAA&#xA;" path="m181830,l393335,,333142,78168r-151312,c156323,78168,135011,85239,118288,98533v-16710,13721,-25071,31601,-25071,52799c93217,172532,101578,189578,118288,202883v16723,13295,38035,19951,63542,19951l393335,222834r-60193,78083l181830,300917v-52253,,-95722,-14690,-129999,-43657c17145,227873,,191239,,147587,,103946,17145,68137,51000,40969,84855,13794,128747,,181830,xe" fillcolor="black" stroked="f" strokeweight="0"><v:stroke miterlimit="83231f" joinstyle="miter"/><v:path arrowok="t" textboxrect="0,0,393335,300917"/></v:shape><v:shape id="Shape 1149" o:spid="_x0000_s1034" style="position:absolute;left:25536;top:5937;width:5016;height:3018;visibility:visible;mso-wrap-style:square;v-text-anchor:top" coordsize="501599,301791" o:gfxdata="UEsDBBQABgAIAAAAIQDb4fbL7gAAAIUBAAATAAAAW0NvbnRlbnRfVHlwZXNdLnhtbHyQz07DMAyH&#xA;70i8Q+QralM4IITa7kDhCAiNB7ASt43WOlEcyvb2pNu4IODoPz9/n1xv9vOkForiPDdwXVagiI23&#xA;jocG3rdPxR0oScgWJ8/UwIEENu3lRb09BBKV0ywNjCmFe63FjDSjlD4Q50nv44wpl3HQAc0OB9I3&#xA;VXWrjedEnIq03oC27qjHjympx31un0wiTQLq4bS4shrAECZnMGVTvbD9QSnOhDInjzsyuiBXWQP0&#xA;r4R18jfgnHvJr4nOknrFmJ5xzhraRtHWf3Kkpfz/yGo5S+H73hkquyhdjr3R8m2lj09svwAAAP//&#xA;AwBQSwMEFAAGAAgAAAAhAFr0LFu/AAAAFQEAAAsAAABfcmVscy8ucmVsc2zPwWrDMAwG4Ptg72B0&#xA;X5TuUMaI01uh19I+gLGVxCy2jGSy9e1nemrHjpL4P0nD4SetZiPRyNnCruvBUPYcYp4tXC/Htw8w&#xA;Wl0ObuVMFm6kcBhfX4Yzra62kC6xqGlKVgtLreUTUf1CyWnHhXKbTCzJ1VbKjMX5LzcTvvf9HuXR&#xA;gPHJNKdgQU5hB+ZyK23zHztFL6w81c5zQp6m6P9TMfB3PtPWFCczVQtB9N4U2rp2HOA44NMz4y8A&#xA;AAD//wMAUEsDBBQABgAIAAAAIQCR8XPWxAAAAN0AAAAPAAAAZHJzL2Rvd25yZXYueG1sRE/NasJA&#xA;EL4LvsMyQm91k1bUptmItAheVGr7AEN2mkSzs2F3NWmfvisUvM3H9zv5ajCtuJLzjWUF6TQBQVxa&#xA;3XCl4Otz87gE4QOyxtYyKfghD6tiPMox07bnD7oeQyViCPsMFdQhdJmUvqzJoJ/ajjhy39YZDBG6&#xA;SmqHfQw3rXxKkrk02HBsqLGjt5rK8/FiFCwWz8u1bHb7jTm8u9+L7dOT7ZV6mAzrVxCBhnAX/7u3&#xA;Os5PZy9w+yaeIIs/AAAA//8DAFBLAQItABQABgAIAAAAIQDb4fbL7gAAAIUBAAATAAAAAAAAAAAA&#xA;AAAAAAAAAABbQ29udGVudF9UeXBlc10ueG1sUEsBAi0AFAAGAAgAAAAhAFr0LFu/AAAAFQEAAAsA&#xA;AAAAAAAAAAAAAAAAHwEAAF9yZWxzLy5yZWxzUEsBAi0AFAAGAAgAAAAhAJHxc9bEAAAA3QAAAA8A&#xA;AAAAAAAAAAAAAAAABwIAAGRycy9kb3ducmV2LnhtbFBLBQYAAAAAAwADALcAAAD4AgAAAAA=&#xA;" path="m253312,v11276,,22988,3756,34686,10848c298443,17102,306805,25034,313083,34210l501599,301791r-354046,l203974,223628r125818,l251624,115567,115782,301791,,301791,193106,34210v6278,-8762,14640,-16682,25507,-23362c230733,3756,242023,,253312,xe" fillcolor="black" stroked="f" strokeweight="0"><v:stroke miterlimit="83231f" joinstyle="miter"/><v:path arrowok="t" textboxrect="0,0,501599,301791"/></v:shape><v:shape id="Shape 1150" o:spid="_x0000_s1035" style="position:absolute;left:17558;top:5920;width:3737;height:3009;visibility:visible;mso-wrap-style:square;v-text-anchor:top" coordsize="373695,300918" o:gfxdata="UEsDBBQABgAIAAAAIQDb4fbL7gAAAIUBAAATAAAAW0NvbnRlbnRfVHlwZXNdLnhtbHyQz07DMAyH&#xA;70i8Q+QralM4IITa7kDhCAiNB7ASt43WOlEcyvb2pNu4IODoPz9/n1xv9vOkForiPDdwXVagiI23&#xA;jocG3rdPxR0oScgWJ8/UwIEENu3lRb09BBKV0ywNjCmFe63FjDSjlD4Q50nv44wpl3HQAc0OB9I3&#xA;VXWrjedEnIq03oC27qjHjympx31un0wiTQLq4bS4shrAECZnMGVTvbD9QSnOhDInjzsyuiBXWQP0&#xA;r4R18jfgnHvJr4nOknrFmJ5xzhraRtHWf3Kkpfz/yGo5S+H73hkquyhdjr3R8m2lj09svwAAAP//&#xA;AwBQSwMEFAAGAAgAAAAhAFr0LFu/AAAAFQEAAAsAAABfcmVscy8ucmVsc2zPwWrDMAwG4Ptg72B0&#xA;X5TuUMaI01uh19I+gLGVxCy2jGSy9e1nemrHjpL4P0nD4SetZiPRyNnCruvBUPYcYp4tXC/Htw8w&#xA;Wl0ObuVMFm6kcBhfX4Yzra62kC6xqGlKVgtLreUTUf1CyWnHhXKbTCzJ1VbKjMX5LzcTvvf9HuXR&#xA;gPHJNKdgQU5hB+ZyK23zHztFL6w81c5zQp6m6P9TMfB3PtPWFCczVQtB9N4U2rp2HOA44NMz4y8A&#xA;AAD//wMAUEsDBBQABgAIAAAAIQBREKU6yAAAAN0AAAAPAAAAZHJzL2Rvd25yZXYueG1sRI9PS8NA&#xA;EMXvgt9hGaE3u4nQIrHbUhVt6aHQP0K9jdkxG8zOxuy2Tb995yB4m+G9ee83k1nvG3WiLtaBDeTD&#xA;DBRxGWzNlYH97u3+EVRMyBabwGTgQhFm09ubCRY2nHlDp22qlIRwLNCAS6kttI6lI49xGFpi0b5D&#xA;5zHJ2lXadniWcN/ohywba481S4PDll4clT/bozcQ5qvP/cezP7y79VdO48Xr4fK7M2Zw18+fQCXq&#xA;07/573ppBT8fCb98IyPo6RUAAP//AwBQSwECLQAUAAYACAAAACEA2+H2y+4AAACFAQAAEwAAAAAA&#xA;AAAAAAAAAAAAAAAAW0NvbnRlbnRfVHlwZXNdLnhtbFBLAQItABQABgAIAAAAIQBa9CxbvwAAABUB&#xA;AAALAAAAAAAAAAAAAAAAAB8BAABfcmVscy8ucmVsc1BLAQItABQABgAIAAAAIQBREKU6yAAAAN0A&#xA;AAAPAAAAAAAAAAAAAAAAAAcCAABkcnMvZG93bnJldi54bWxQSwUGAAAAAAMAAwC3AAAA/AIAAAAA&#xA;" path="m,l251226,v33855,,62276,7950,85264,23407c361152,40134,373273,62282,373273,90097v,27474,-12121,49717,-36783,66512c313502,172146,285081,180119,251226,180119r-117461,c124987,180119,116628,181350,108684,183819v-10866,3693,-16302,9033,-16302,16017l92382,222834r281313,l313502,300918r-309314,l4188,199836v,-28949,12953,-52883,39288,-71773c68141,110852,98232,102029,133765,102029r117461,c262502,102029,268358,97915,268358,90097v,-7814,-5856,-11922,-17132,-11922l60198,78175,,xe" fillcolor="#0077ab" stroked="f" strokeweight="0"><v:stroke miterlimit="83231f" joinstyle="miter"/><v:path arrowok="t" textboxrect="0,0,373695,300918"/></v:shape><v:shape id="Shape 1151" o:spid="_x0000_s1036" style="position:absolute;left:5702;top:5920;width:2204;height:3009;visibility:visible;mso-wrap-style:square;v-text-anchor:top" coordsize="220402,300918" o:gfxdata="UEsDBBQABgAIAAAAIQDb4fbL7gAAAIUBAAATAAAAW0NvbnRlbnRfVHlwZXNdLnhtbHyQz07DMAyH&#xA;70i8Q+QralM4IITa7kDhCAiNB7ASt43WOlEcyvb2pNu4IODoPz9/n1xv9vOkForiPDdwXVagiI23&#xA;jocG3rdPxR0oScgWJ8/UwIEENu3lRb09BBKV0ywNjCmFe63FjDSjlD4Q50nv44wpl3HQAc0OB9I3&#xA;VXWrjedEnIq03oC27qjHjympx31un0wiTQLq4bS4shrAECZnMGVTvbD9QSnOhDInjzsyuiBXWQP0&#xA;r4R18jfgnHvJr4nOknrFmJ5xzhraRtHWf3Kkpfz/yGo5S+H73hkquyhdjr3R8m2lj09svwAAAP//&#xA;AwBQSwMEFAAGAAgAAAAhAFr0LFu/AAAAFQEAAAsAAABfcmVscy8ucmVsc2zPwWrDMAwG4Ptg72B0&#xA;X5TuUMaI01uh19I+gLGVxCy2jGSy9e1nemrHjpL4P0nD4SetZiPRyNnCruvBUPYcYp4tXC/Htw8w&#xA;Wl0ObuVMFm6kcBhfX4Yzra62kC6xqGlKVgtLreUTUf1CyWnHhXKbTCzJ1VbKjMX5LzcTvvf9HuXR&#xA;gPHJNKdgQU5hB+ZyK23zHztFL6w81c5zQp6m6P9TMfB3PtPWFCczVQtB9N4U2rp2HOA44NMz4y8A&#xA;AAD//wMAUEsDBBQABgAIAAAAIQCCO6fkwwAAAN0AAAAPAAAAZHJzL2Rvd25yZXYueG1sRE9LawIx&#xA;EL4X/A9hBC9FsytYZDWKKEXprT7wOmzGzepmEjepbv99Uyj0Nh/fc+bLzjbiQW2oHSvIRxkI4tLp&#xA;misFx8P7cAoiRGSNjWNS8E0BloveyxwL7Z78SY99rEQK4VCgAhOjL6QMpSGLYeQ8ceIurrUYE2wr&#xA;qVt8pnDbyHGWvUmLNacGg57Whsrb/ssqOHe319yUJ3+Xu834up1Orh/klRr0u9UMRKQu/ov/3Dud&#xA;5ueTHH6/SSfIxQ8AAAD//wMAUEsBAi0AFAAGAAgAAAAhANvh9svuAAAAhQEAABMAAAAAAAAAAAAA&#xA;AAAAAAAAAFtDb250ZW50X1R5cGVzXS54bWxQSwECLQAUAAYACAAAACEAWvQsW78AAAAVAQAACwAA&#xA;AAAAAAAAAAAAAAAfAQAAX3JlbHMvLnJlbHNQSwECLQAUAAYACAAAACEAgjun5MMAAADdAAAADwAA&#xA;AAAAAAAAAAAAAAAHAgAAZHJzL2Rvd25yZXYueG1sUEsFBgAAAAADAAMAtwAAAPcCAAAAAA==&#xA;" path="m182240,r38162,l220402,78175r-38162,c156326,78175,135013,84820,118291,98535v-16716,13720,-25080,31599,-25080,52797c93211,172532,101575,189992,118291,202884v16722,13294,38035,19950,63949,19950l220402,222834r,78084l182240,300918v-52662,,-96133,-14691,-130411,-43658c17136,227873,,191241,,147587,,103948,17136,68137,50995,40969,85273,13795,129157,,182240,xe" stroked="f" strokeweight="0"><v:stroke miterlimit="83231f" joinstyle="miter"/><v:path arrowok="t" textboxrect="0,0,220402,300918"/></v:shape><v:shape id="Shape 1152" o:spid="_x0000_s1037" style="position:absolute;left:14119;top:5920;width:3273;height:3009;visibility:visible;mso-wrap-style:square;v-text-anchor:top" coordsize="327285,300918" o:gfxdata="UEsDBBQABgAIAAAAIQDb4fbL7gAAAIUBAAATAAAAW0NvbnRlbnRfVHlwZXNdLnhtbHyQz07DMAyH&#xA;70i8Q+QralM4IITa7kDhCAiNB7ASt43WOlEcyvb2pNu4IODoPz9/n1xv9vOkForiPDdwXVagiI23&#xA;jocG3rdPxR0oScgWJ8/UwIEENu3lRb09BBKV0ywNjCmFe63FjDSjlD4Q50nv44wpl3HQAc0OB9I3&#xA;VXWrjedEnIq03oC27qjHjympx31un0wiTQLq4bS4shrAECZnMGVTvbD9QSnOhDInjzsyuiBXWQP0&#xA;r4R18jfgnHvJr4nOknrFmJ5xzhraRtHWf3Kkpfz/yGo5S+H73hkquyhdjr3R8m2lj09svwAAAP//&#xA;AwBQSwMEFAAGAAgAAAAhAFr0LFu/AAAAFQEAAAsAAABfcmVscy8ucmVsc2zPwWrDMAwG4Ptg72B0&#xA;X5TuUMaI01uh19I+gLGVxCy2jGSy9e1nemrHjpL4P0nD4SetZiPRyNnCruvBUPYcYp4tXC/Htw8w&#xA;Wl0ObuVMFm6kcBhfX4Yzra62kC6xqGlKVgtLreUTUf1CyWnHhXKbTCzJ1VbKjMX5LzcTvvf9HuXR&#xA;gPHJNKdgQU5hB+ZyK23zHztFL6w81c5zQp6m6P9TMfB3PtPWFCczVQtB9N4U2rp2HOA44NMz4y8A&#xA;AAD//wMAUEsDBBQABgAIAAAAIQARKHvlvgAAAN0AAAAPAAAAZHJzL2Rvd25yZXYueG1sRE/LqsIw&#xA;EN0L/kMYwY1oqqBoNYpckLpxUfUDhmZsi82kJLla/94Igrs5nOdsdp1pxIOcry0rmE4SEMSF1TWX&#xA;Cq6Xw3gJwgdkjY1lUvAiD7ttv7fBVNsn5/Q4h1LEEPYpKqhCaFMpfVGRQT+xLXHkbtYZDBG6UmqH&#xA;zxhuGjlLkoU0WHNsqLClv4qK+/nfKMhdwVmWjfIyaaw2Dk8+H62UGg66/RpEoC78xF/3Ucf50/kM&#xA;Pt/EE+T2DQAA//8DAFBLAQItABQABgAIAAAAIQDb4fbL7gAAAIUBAAATAAAAAAAAAAAAAAAAAAAA&#xA;AABbQ29udGVudF9UeXBlc10ueG1sUEsBAi0AFAAGAAgAAAAhAFr0LFu/AAAAFQEAAAsAAAAAAAAA&#xA;AAAAAAAAHwEAAF9yZWxzLy5yZWxzUEsBAi0AFAAGAAgAAAAhABEoe+W+AAAA3QAAAA8AAAAAAAAA&#xA;AAAAAAAABwIAAGRycy9kb3ducmV2LnhtbFBLBQYAAAAAAwADALcAAADyAgAAAAA=&#xA;" path="m,l327285,,267093,78175r-173468,l93625,109558r219031,l252458,187643r-158833,l93625,222834r233660,l267093,300918,,300918,,xe" stroked="f" strokeweight="0"><v:stroke miterlimit="83231f" joinstyle="miter"/><v:path arrowok="t" textboxrect="0,0,327285,300918"/></v:shape><v:shape id="Shape 1153" o:spid="_x0000_s1038" style="position:absolute;left:10330;top:5920;width:3583;height:3035;visibility:visible;mso-wrap-style:square;v-text-anchor:top" coordsize="358222,303471" o:gfxdata="UEsDBBQABgAIAAAAIQDb4fbL7gAAAIUBAAATAAAAW0NvbnRlbnRfVHlwZXNdLnhtbHyQz07DMAyH&#xA;70i8Q+QralM4IITa7kDhCAiNB7ASt43WOlEcyvb2pNu4IODoPz9/n1xv9vOkForiPDdwXVagiI23&#xA;jocG3rdPxR0oScgWJ8/UwIEENu3lRb09BBKV0ywNjCmFe63FjDSjlD4Q50nv44wpl3HQAc0OB9I3&#xA;VXWrjedEnIq03oC27qjHjympx31un0wiTQLq4bS4shrAECZnMGVTvbD9QSnOhDInjzsyuiBXWQP0&#xA;r4R18jfgnHvJr4nOknrFmJ5xzhraRtHWf3Kkpfz/yGo5S+H73hkquyhdjr3R8m2lj09svwAAAP//&#xA;AwBQSwMEFAAGAAgAAAAhAFr0LFu/AAAAFQEAAAsAAABfcmVscy8ucmVsc2zPwWrDMAwG4Ptg72B0&#xA;X5TuUMaI01uh19I+gLGVxCy2jGSy9e1nemrHjpL4P0nD4SetZiPRyNnCruvBUPYcYp4tXC/Htw8w&#xA;Wl0ObuVMFm6kcBhfX4Yzra62kC6xqGlKVgtLreUTUf1CyWnHhXKbTCzJ1VbKjMX5LzcTvvf9HuXR&#xA;gPHJNKdgQU5hB+ZyK23zHztFL6w81c5zQp6m6P9TMfB3PtPWFCczVQtB9N4U2rp2HOA44NMz4y8A&#xA;AAD//wMAUEsDBBQABgAIAAAAIQBW3U6vwgAAAN0AAAAPAAAAZHJzL2Rvd25yZXYueG1sRE9Li8Iw&#xA;EL4v+B/CCN7W1BUXqUZRQVHci6/72Ewf2ky6TdT6783Cgrf5+J4znjamFHeqXWFZQa8bgSBOrC44&#xA;U3A8LD+HIJxH1lhaJgVPcjCdtD7GGGv74B3d9z4TIYRdjApy76tYSpfkZNB1bUUcuNTWBn2AdSZ1&#xA;jY8Qbkr5FUXf0mDBoSHHihY5Jdf9zShY/Z6387RYm34a3c7X7HL62TyXSnXazWwEwlPj3+J/91qH&#xA;+b1BH/6+CSfIyQsAAP//AwBQSwECLQAUAAYACAAAACEA2+H2y+4AAACFAQAAEwAAAAAAAAAAAAAA&#xA;AAAAAAAAW0NvbnRlbnRfVHlwZXNdLnhtbFBLAQItABQABgAIAAAAIQBa9CxbvwAAABUBAAALAAAA&#xA;AAAAAAAAAAAAAB8BAABfcmVscy8ucmVsc1BLAQItABQABgAIAAAAIQBW3U6vwgAAAN0AAAAPAAAA&#xA;AAAAAAAAAAAAAAcCAABkcnMvZG93bnJldi54bWxQSwUGAAAAAAMAAwC3AAAA9gIAAAAA&#xA;" path="m264591,r93631,l358222,262508v,27169,-12540,40963,-37201,40963c303045,303471,285909,296781,270026,283407l93631,135854r,165523l,301377,,38875c,27595,3342,18397,10447,11292,17557,4182,28003,421,40962,421v17137,,32605,5850,47239,17976l264591,165945,264591,xe" stroked="f" strokeweight="0"><v:stroke miterlimit="83231f" joinstyle="miter"/><v:path arrowok="t" textboxrect="0,0,358222,303471"/></v:shape><v:shape id="Shape 1154" o:spid="_x0000_s1039" style="position:absolute;left:7906;top:5920;width:2200;height:3009;visibility:visible;mso-wrap-style:square;v-text-anchor:top" coordsize="219988,300918" o:gfxdata="UEsDBBQABgAIAAAAIQDb4fbL7gAAAIUBAAATAAAAW0NvbnRlbnRfVHlwZXNdLnhtbHyQz07DMAyH&#xA;70i8Q+QralM4IITa7kDhCAiNB7ASt43WOlEcyvb2pNu4IODoPz9/n1xv9vOkForiPDdwXVagiI23&#xA;jocG3rdPxR0oScgWJ8/UwIEENu3lRb09BBKV0ywNjCmFe63FjDSjlD4Q50nv44wpl3HQAc0OB9I3&#xA;VXWrjedEnIq03oC27qjHjympx31un0wiTQLq4bS4shrAECZnMGVTvbD9QSnOhDInjzsyuiBXWQP0&#xA;r4R18jfgnHvJr4nOknrFmJ5xzhraRtHWf3Kkpfz/yGo5S+H73hkquyhdjr3R8m2lj09svwAAAP//&#xA;AwBQSwMEFAAGAAgAAAAhAFr0LFu/AAAAFQEAAAsAAABfcmVscy8ucmVsc2zPwWrDMAwG4Ptg72B0&#xA;X5TuUMaI01uh19I+gLGVxCy2jGSy9e1nemrHjpL4P0nD4SetZiPRyNnCruvBUPYcYp4tXC/Htw8w&#xA;Wl0ObuVMFm6kcBhfX4Yzra62kC6xqGlKVgtLreUTUf1CyWnHhXKbTCzJ1VbKjMX5LzcTvvf9HuXR&#xA;gPHJNKdgQU5hB+ZyK23zHztFL6w81c5zQp6m6P9TMfB3PtPWFCczVQtB9N4U2rp2HOA44NMz4y8A&#xA;AAD//wMAUEsDBBQABgAIAAAAIQBROVpPwwAAAN0AAAAPAAAAZHJzL2Rvd25yZXYueG1sRE/NasJA&#xA;EL4X+g7LCF5Ks4lYKdFVilD04MHGPMCQnfxgdjbNrkl8e7dQ8DYf3+9sdpNpxUC9aywrSKIYBHFh&#xA;dcOVgvzy/f4Jwnlkja1lUnAnB7vt68sGU21H/qEh85UIIexSVFB736VSuqImgy6yHXHgStsb9AH2&#xA;ldQ9jiHctHIRxytpsOHQUGNH+5qKa3YzCpZv18zlzf7W3ePf5HzgojxJp9R8Nn2tQXia/FP87z7q&#xA;MD/5WMLfN+EEuX0AAAD//wMAUEsBAi0AFAAGAAgAAAAhANvh9svuAAAAhQEAABMAAAAAAAAAAAAA&#xA;AAAAAAAAAFtDb250ZW50X1R5cGVzXS54bWxQSwECLQAUAAYACAAAACEAWvQsW78AAAAVAQAACwAA&#xA;AAAAAAAAAAAAAAAfAQAAX3JlbHMvLnJlbHNQSwECLQAUAAYACAAAACEAUTlaT8MAAADdAAAADwAA&#xA;AAAAAAAAAAAAAAAHAgAAZHJzL2Rvd25yZXYueG1sUEsFBgAAAAADAAMAtwAAAPcCAAAAAA==&#xA;" path="m,l38157,v53088,,96972,13795,130831,40969c202846,68137,219988,103948,219988,147587v,43654,-17142,80286,-51414,109253c133876,286227,90411,300918,38157,300918l,300918,,222834r38157,c64076,222834,85389,216178,102111,203298v16717,-13306,25080,-30766,25080,-51966c127191,130134,118828,112669,102111,98949,84975,85239,63651,78175,38157,78175l,78175,,xe" stroked="f" strokeweight="0"><v:stroke miterlimit="83231f" joinstyle="miter"/><v:path arrowok="t" textboxrect="0,0,219988,300918"/></v:shape><v:shape id="Shape 10135" o:spid="_x0000_s1040" style="position:absolute;left:70200;top:5400;width:360;height:4028;visibility:visible;mso-wrap-style:square;v-text-anchor:top" coordsize="35999,402872" o:gfxdata="UEsDBBQABgAIAAAAIQDb4fbL7gAAAIUBAAATAAAAW0NvbnRlbnRfVHlwZXNdLnhtbHyQz07DMAyH&#xA;70i8Q+QralM4IITa7kDhCAiNB7ASt43WOlEcyvb2pNu4IODoPz9/n1xv9vOkForiPDdwXVagiI23&#xA;jocG3rdPxR0oScgWJ8/UwIEENu3lRb09BBKV0ywNjCmFe63FjDSjlD4Q50nv44wpl3HQAc0OB9I3&#xA;VXWrjedEnIq03oC27qjHjympx31un0wiTQLq4bS4shrAECZnMGVTvbD9QSnOhDInjzsyuiBXWQP0&#xA;r4R18jfgnHvJr4nOknrFmJ5xzhraRtHWf3Kkpfz/yGo5S+H73hkquyhdjr3R8m2lj09svwAAAP//&#xA;AwBQSwMEFAAGAAgAAAAhAFr0LFu/AAAAFQEAAAsAAABfcmVscy8ucmVsc2zPwWrDMAwG4Ptg72B0&#xA;X5TuUMaI01uh19I+gLGVxCy2jGSy9e1nemrHjpL4P0nD4SetZiPRyNnCruvBUPYcYp4tXC/Htw8w&#xA;Wl0ObuVMFm6kcBhfX4Yzra62kC6xqGlKVgtLreUTUf1CyWnHhXKbTCzJ1VbKjMX5LzcTvvf9HuXR&#xA;gPHJNKdgQU5hB+ZyK23zHztFL6w81c5zQp6m6P9TMfB3PtPWFCczVQtB9N4U2rp2HOA44NMz4y8A&#xA;AAD//wMAUEsDBBQABgAIAAAAIQDd9p3nxAAAAN4AAAAPAAAAZHJzL2Rvd25yZXYueG1sRI9Bi8Iw&#xA;EIXvC/6HMIK3NVFRlmoUFYW9eFi7P2BoxrbaTEoSa/33ZkHY2wzvfW/erDa9bURHPtSONUzGCgRx&#xA;4UzNpYbf/Pj5BSJEZIONY9LwpACb9eBjhZlxD/6h7hxLkUI4ZKihirHNpAxFRRbD2LXESbs4bzGm&#xA;1ZfSeHykcNvIqVILabHmdKHClvYVFbfz3aYa8XJYyLz25W56Uruuu962p1zr0bDfLkFE6uO/+U1/&#xA;m8SpyWwOf++kGeT6BQAA//8DAFBLAQItABQABgAIAAAAIQDb4fbL7gAAAIUBAAATAAAAAAAAAAAA&#xA;AAAAAAAAAABbQ29udGVudF9UeXBlc10ueG1sUEsBAi0AFAAGAAgAAAAhAFr0LFu/AAAAFQEAAAsA&#xA;AAAAAAAAAAAAAAAAHwEAAF9yZWxzLy5yZWxzUEsBAi0AFAAGAAgAAAAhAN32nefEAAAA3gAAAA8A&#xA;AAAAAAAAAAAAAAAABwIAAGRycy9kb3ducmV2LnhtbFBLBQYAAAAAAwADALcAAAD4AgAAAAA=&#xA;" path="m,l35999,r,402872l,402872,,e" fillcolor="#0070a3" stroked="f" strokeweight="0"><v:stroke miterlimit="83231f" joinstyle="miter"/><v:path arrowok="t" textboxrect="0,0,35999,402872"/></v:shape><w10:wrap type="topAndBottom" anchorx="page" anchory="page"/></v:group></w:pict></mc:Fallback></mc:AlternateContent></w:r><w:r><w:t>2.4 These Conditions may not be varied except by the written agreement of a Director of the Seller. 2.5 These Conditions represent the whole of the</w:t></w:r></w:p><w:p w14:paraId="4C4D04EA" w14:textId="77777777" w:rsidR="00EF5116" w:rsidRDefault="00000000"><w:pPr><w:spacing w:after="460"/><w:ind w:left="-5" w:right="200"/></w:pPr><w:r><w:t>agreement between the Seller and the Buyer. They supersede any other conditions previously issued.</w:t></w:r></w:p><w:p w14:paraId="41C252B5" w14:textId="77777777" w:rsidR="00EF5116" w:rsidRDefault="00000000"><w:pPr><w:pStyle w:val="Heading2"/><w:ind w:left="-5"/></w:pPr><w:r><w:lastRenderedPageBreak/><w:t>3. Price</w:t></w:r></w:p><w:p w14:paraId="56EBD174" w14:textId="77777777" w:rsidR="00EF5116" w:rsidRDefault="00000000"><w:pPr><w:spacing w:after="0"/><w:ind w:left="-5"/></w:pPr><w:r><w:t>The Price shall be the price quoted on the Seller’s confirmation of order. The Price is exclusive of VAT which shall be due at the rate in force on the date of the</w:t></w:r></w:p><w:p w14:paraId="2FCF37F7" w14:textId="77777777" w:rsidR="00EF5116" w:rsidRDefault="00000000"><w:pPr><w:spacing w:after="490"/><w:ind w:left="-5"/></w:pPr><w:r><w:t>Seller’s invoice.</w:t></w:r></w:p><w:p w14:paraId="3BA2DCFE" w14:textId="77777777" w:rsidR="00EF5116" w:rsidRDefault="00000000"><w:pPr><w:pStyle w:val="Heading2"/><w:ind w:left="-5"/></w:pPr><w:r><w:t>4. Payment and Interest</w:t></w:r></w:p><w:p w14:paraId="7204C314" w14:textId="77777777" w:rsidR="00EF5116" w:rsidRDefault="00000000"><w:pPr><w:ind w:left="-5"/></w:pPr><w:r><w:t>4.1 Payment of the Price and VAT shall be due within 30 days of the date of the Seller’s invoice, unless otherwise stated.</w:t></w:r></w:p><w:p w14:paraId="3BBCC90E" w14:textId="77777777" w:rsidR="00EF5116" w:rsidRDefault="00000000"><w:pPr><w:ind w:left="-5"/></w:pPr><w:r><w:t xml:space="preserve">4.2 Interest on overdue invoices shall accrue from the date when payment becomes due calculated </w:t></w:r><w:proofErr w:type="gramStart"/><w:r><w:t>on a daily basis</w:t></w:r><w:proofErr w:type="gramEnd"/><w:r><w:t xml:space="preserve"> until the date of payment at the rate of 8% per annum above the Bank of England base rate from time to time in force. Such interest shall accrue after as well as before any judgment.</w:t></w:r></w:p><w:p w14:paraId="547A026A" w14:textId="77777777" w:rsidR="00EF5116" w:rsidRDefault="00000000"><w:pPr><w:spacing w:after="492"/><w:ind w:left="-5" w:right="402"/></w:pPr><w:r><w:t xml:space="preserve">4.3 The Buyer shall pay all accounts in full and not exercise any rights of set-off or </w:t></w:r><w:proofErr w:type="gramStart"/><w:r><w:t>counter-claim</w:t></w:r><w:proofErr w:type="gramEnd"/><w:r><w:t xml:space="preserve"> against invoices submitted by the Seller.</w:t></w:r><w:bookmarkStart w:id="0" w:name="OpenAt"/><w:bookmarkEnd w:id="0"/></w:p><w:p w14:paraId="67BB7EA9" w14:textId="77777777" w:rsidR="00EF5116" w:rsidRDefault="00000000"><w:pPr><w:pStyle w:val="Heading2"/><w:ind w:left="-5"/></w:pPr><w:r><w:t>5. Goods</w:t></w:r></w:p><w:p w14:paraId="1EF717A7" w14:textId="77777777" w:rsidR="00EF5116" w:rsidRDefault="00000000"><w:pPr><w:spacing w:after="654"/><w:ind w:left="-5"/></w:pPr><w:r><w:t>The quantity and description of the Goods shall be as set out in the Seller’s confirmation of order.</w:t></w:r></w:p><w:p w14:paraId="0853179F" w14:textId="77777777" w:rsidR="00EF5116" w:rsidRDefault="00000000"><w:pPr><w:pStyle w:val="Heading2"/><w:ind w:left="-5"/></w:pPr><w:r><w:t>6. Warranties</w:t></w:r></w:p><w:p w14:paraId="76BDD9D8" w14:textId="77777777" w:rsidR="00EF5116" w:rsidRDefault="00000000"><w:pPr><w:spacing w:after="649"/><w:ind w:left="-5"/></w:pPr><w:r><w:t>The Seller warrants that the Goods will at the time of delivery correspond to the description given by the Seller in the confirmation of order. [Except where the Buyer is dealing as a consumer (as defined in section 12 of the Unfair Contract Terms Act 1977), all other warranties, conditions or terms relating to fitness for purpose, quality or condition of the Goods are excluded].</w:t></w:r></w:p><w:p w14:paraId="6C5B1E50" w14:textId="77777777" w:rsidR="00EF5116" w:rsidRDefault="00000000"><w:pPr><w:pStyle w:val="Heading2"/><w:ind w:left="-5"/></w:pPr><w:r><w:t>7. Delivery of the Goods</w:t></w:r></w:p><w:p w14:paraId="47E5D81F" w14:textId="77777777" w:rsidR="00EF5116" w:rsidRDefault="00000000"><w:pPr><w:ind w:left="-5"/></w:pPr><w:r><w:t>7.1 Delivery of the Goods shall be made to the Buyer’s address. The Buyer shall make all arrangements necessary to take delivery of the Goods on the day notified by the Seller for delivery.</w:t></w:r></w:p><w:p w14:paraId="57A107BC" w14:textId="77777777" w:rsidR="00EF5116" w:rsidRDefault="00000000"><w:pPr><w:ind w:left="-5" w:right="110"/></w:pPr><w:r><w:t xml:space="preserve">7.2 The Seller undertakes to use its reasonable endeavours to despatch the Goods on an agreed delivery </w:t></w:r><w:proofErr w:type="gramStart"/><w:r><w:t>date, but</w:t></w:r><w:proofErr w:type="gramEnd"/><w:r><w:t xml:space="preserve"> does not guarantee to do so. Time of delivery shall not be of the essence of the contract.</w:t></w:r></w:p><w:p w14:paraId="57B29568" w14:textId="77777777" w:rsidR="00EF5116" w:rsidRDefault="00000000"><w:pPr><w:ind w:left="-5"/></w:pPr><w:r><w:t>7.3 The Seller shall not be liable to the Buyer for any loss or damage whether arising directly or indirectly from the late delivery or short delivery of the Goods. If short delivery does take place, the Buyer undertakes not to reject the Goods but to accept the Goods delivered as part performance of the contract.</w:t></w:r></w:p><w:p w14:paraId="791A9603" w14:textId="77777777" w:rsidR="00EF5116" w:rsidRDefault="00000000"><w:pPr><w:spacing w:after="491"/><w:ind w:left="-5"/></w:pPr><w:r><w:t>7.4 If the Buyer fails to take delivery of the Goods on the agreed delivery date or, if no specific delivery date has been agreed, when the Goods are ready for despatch, the Seller shall be entitled to store and insure the Goods and to charge the Buyer the reasonable costs of so doing.</w:t></w:r></w:p><w:p w14:paraId="0BF9EC20" w14:textId="77777777" w:rsidR="00EF5116" w:rsidRDefault="00000000"><w:pPr><w:pStyle w:val="Heading2"/><w:spacing w:after="75"/><w:ind w:left="-5"/></w:pPr><w:r><w:t>8. Acceptance of the Goods</w:t></w:r></w:p><w:p w14:paraId="0DE444FF" w14:textId="77777777" w:rsidR="00EF5116" w:rsidRDefault="00000000"><w:pPr><w:ind w:left="-5"/></w:pPr><w:r><w:t>8.1 The Buyer shall be deemed to have accepted the Goods 48 hours after delivery to the Buyer.</w:t></w:r></w:p><w:p w14:paraId="0937950D" w14:textId="77777777" w:rsidR="00EF5116" w:rsidRDefault="00000000"><w:pPr><w:ind w:left="-5"/></w:pPr><w:r><w:t>8.2 The Buyer shall carry out a thorough inspection of the Goods within 48 hours of delivery and shall give written notification to the Seller within 5 working days of delivery of the Goods of any defects which a reasonable examination would have revealed.</w:t></w:r></w:p><w:p w14:paraId="345DBFDB" w14:textId="53DB95CF" w:rsidR="00EF5116" w:rsidRDefault="00000000"><w:pPr><w:spacing w:after="553"/><w:ind w:left="-5"/></w:pPr><w:r><w:rPr><w:noProof/><w:color w:val="000000"/><w:sz w:val="22"/></w:rPr><mc:AlternateContent><mc:Choice Requires="wpg"><w:drawing><wp:anchor distT="0" distB="0" distL="114300" distR="114300" simplePos="0" relativeHeight="251660288" behindDoc="0" locked="0" layoutInCell="1" allowOverlap="1" wp14:anchorId="7035D1C6" wp14:editId="2A0EFE17"><wp:simplePos x="0" y="0"/><wp:positionH relativeFrom="page"><wp:posOffset>0</wp:posOffset></wp:positionH><wp:positionV relativeFrom="page"><wp:posOffset>0</wp:posOffset></wp:positionV><wp:extent cx="7560005" cy="216002"/><wp:effectExtent l="0" t="0" r="0" b="0"/><wp:wrapTopAndBottom/><wp:docPr id="9009" name="Group 9009"/><wp:cNvGraphicFramePr/><a:graphic xmlns:a="http://schemas.openxmlformats.org/drawingml/2006/main"><a:graphicData uri="http://schemas.microsoft.com/office/word/2010/wordprocessingGroup"><wpg:wgp><wpg:cNvGrpSpPr/><wpg:grpSpPr><a:xfrm><a:off x="0" y="0"/><a:ext cx="7560005" cy="216002"/><a:chOff x="0" y="0"/><a:chExt cx="7560005" cy="216002"/></a:xfrm></wpg:grpSpPr><wps:wsp><wps:cNvPr id="10509" name="Shape 10509"/><wps:cNvSpPr/><wps:spPr><a:xfrm><a:off x="0" y="0"/><a:ext cx="7560005" cy="216002"/></a:xfrm><a:custGeom><a:avLst/><a:gdLst/><a:ahLst/><a:cxnLst/><a:rect l="0" t="0" r="0" b="0"/><a:pathLst><a:path w="7560005" h="216002"><a:moveTo><a:pt x="0" y="0"/></a:moveTo><a:lnTo><a:pt x="7560005" y="0"/></a:lnTo><a:lnTo><a:pt x="7560005" y="216002"/></a:lnTo><a:lnTo><a:pt x="0" y="216002"/></a:lnTo><a:lnTo><a:pt x="0" y="0"/></a:lnTo></a:path></a:pathLst></a:custGeom><a:ln w="0" cap="flat"><a:miter lim="127000"/></a:ln></wps:spPr><wps:style><a:lnRef idx="0"><a:srgbClr val="000000"><a:alpha val="0"/></a:srgbClr></a:lnRef><a:fillRef idx="1"><a:srgbClr val="0070A3"/></a:fillRef><a:effectRef idx="0"><a:scrgbClr r="0" g="0" b="0"/></a:effectRef><a:fontRef idx="none"/></wps:style><wps:bodyPr/></wps:wsp></wpg:wgp></a:graphicData></a:graphic></wp:anchor></w:drawing></mc:Choice><mc:Fallback><w:pict><v:group w14:anchorId="0622C3A4" id="Group 9009" o:spid="_x0000_s1026" style="position:absolute;margin-left:0;margin-top:0;width:595.3pt;height:17pt;z-index:251660288;mso-position-horizontal-relative:page;mso-position-vertical-relative:page" coordsize="75600,2160" o:gfxdata="UEsDBBQABgAIAAAAIQC2gziS/gAAAOEBAAATAAAAW0NvbnRlbnRfVHlwZXNdLnhtbJSRQU7DMBBF&#xA;90jcwfIWJU67QAgl6YK0S0CoHGBkTxKLZGx5TGhvj5O2G0SRWNoz/78nu9wcxkFMGNg6quQqL6RA&#xA;0s5Y6ir5vt9lD1JwBDIwOMJKHpHlpr69KfdHjyxSmriSfYz+USnWPY7AufNIadK6MEJMx9ApD/oD&#xA;OlTrorhX2lFEilmcO2RdNtjC5xDF9pCuTyYBB5bi6bQ4syoJ3g9WQ0ymaiLzg5KdCXlKLjvcW893&#xA;SUOqXwnz5DrgnHtJTxOsQfEKIT7DmDSUCaxw7Rqn8787ZsmRM9e2VmPeBN4uqYvTtW7jvijg9N/y&#xA;JsXecLq0q+WD6m8AAAD//wMAUEsDBBQABgAIAAAAIQA4/SH/1gAAAJQBAAALAAAAX3JlbHMvLnJl&#xA;bHOkkMFqwzAMhu+DvYPRfXGawxijTi+j0GvpHsDYimMaW0Yy2fr2M4PBMnrbUb/Q94l/f/hMi1qR&#xA;JVI2sOt6UJgd+ZiDgffL8ekFlFSbvV0oo4EbChzGx4f9GRdb25HMsYhqlCwG5lrLq9biZkxWOiqY&#xA;22YiTra2kYMu1l1tQD30/bPm3wwYN0x18gb45AdQl1tp5j/sFB2T0FQ7R0nTNEV3j6o9feQzro1i&#xA;OWA14Fm+Q8a1a8+Bvu/d/dMb2JY5uiPbhG/ktn4cqGU/er3pcvwCAAD//wMAUEsDBBQABgAIAAAA&#xA;IQDx9SdMbAIAADsGAAAOAAAAZHJzL2Uyb0RvYy54bWykVNtu2zAMfR+wfxD8vtjJkGYzkhTDuuVl&#xA;2Iq1+wBFlmwDukFS4uTvR9G24qZYB7R+kCmJPCKPjri+PSlJjtz51uhNNp8VGeGamarV9Sb78/j9&#xA;w6eM+EB1RaXRfJOduc9ut+/frTtb8oVpjKy4IwCifdnZTdaEYMs896zhivqZsVzDpjBO0QBTV+eV&#xA;ox2gK5kviuIm74yrrDOMew+rd/1mtkV8ITgLv4TwPBC5ySC3gKPDcR/HfLumZe2obVo2pEFfkYWi&#xA;rYZDE9QdDZQcXPsMSrXMGW9EmDGjciNEyzjWANXMi6tqds4cLNZSl11tE01A7RVPr4ZlP487Zx/s&#xA;vQMmOlsDFziLtZyEU/EPWZITUnZOlPFTIAwWV8uboiiWGWGwt5jDZNFzyhog/lkYa769HJiPx+ZP&#xA;kuksyMNfGPBvY+ChoZYjsb4EBu4daStQb7EsPmdEUwVCRRfSLyE16JmI8qUHzt7IUiqWluzgw44b&#xA;5Jsef/jQC7MaLdqMFjvp0XQg7xeFbWmIcTHNaJJucmFNuq+4rcyRPxp0DFe3BlledqWeeqXbH4UB&#xA;vqPH+LeIN/W8yOSf7vBUn+jpP474jpMPGLHa7XowkAGwpxxLHcmAYxiFriMkDfh8VRugHclWgRoW&#xA;K1B2FDMCwy+KsL91tMJZ8kiY1L+5AAHhE4kL3tX7r9KRI41NBz8Ep9I2dFgdcAfX4QzAifGilTJB&#xA;zjH0CnJVfPk4IAzOMY5jv0uRRR/Jhmz6pgetA4oeWx9UloLwZKNDitfQsPGQSbXR3JvqjO0CCYFX&#xA;idRgh8I6hm4aW+B0jl6Xnr/9CwAA//8DAFBLAwQUAAYACAAAACEAsjr3tN0AAAAFAQAADwAAAGRy&#xA;cy9kb3ducmV2LnhtbEyPQUvDQBCF74L/YRnBm92N1WJjNqUU9VSEtoL0Ns1Ok9DsbMhuk/Tfu/Wi&#xA;l4HHe7z3TbYYbSN66nztWEMyUSCIC2dqLjV87d4fXkD4gGywcUwaLuRhkd/eZJgaN/CG+m0oRSxh&#xA;n6KGKoQ2ldIXFVn0E9cSR+/oOoshyq6UpsMhlttGPio1kxZrjgsVtrSqqDhtz1bDx4DDcpq89evT&#xA;cXXZ754/v9cJaX1/Ny5fQQQaw18YrvgRHfLIdHBnNl40GuIj4fdevWSuZiAOGqZPCmSeyf/0+Q8A&#xA;AAD//wMAUEsBAi0AFAAGAAgAAAAhALaDOJL+AAAA4QEAABMAAAAAAAAAAAAAAAAAAAAAAFtDb250&#xA;ZW50X1R5cGVzXS54bWxQSwECLQAUAAYACAAAACEAOP0h/9YAAACUAQAACwAAAAAAAAAAAAAAAAAv&#xA;AQAAX3JlbHMvLnJlbHNQSwECLQAUAAYACAAAACEA8fUnTGwCAAA7BgAADgAAAAAAAAAAAAAAAAAu&#xA;AgAAZHJzL2Uyb0RvYy54bWxQSwECLQAUAAYACAAAACEAsjr3tN0AAAAFAQAADwAAAAAAAAAAAAAA&#xA;AADGBAAAZHJzL2Rvd25yZXYueG1sUEsFBgAAAAAEAAQA8wAAANAFAAAAAA==&#xA;"><v:shape id="Shape 10509" o:spid="_x0000_s1027" style="position:absolute;width:75600;height:2160;visibility:visible;mso-wrap-style:square;v-text-anchor:top" coordsize="7560005,216002" o:gfxdata="UEsDBBQABgAIAAAAIQDb4fbL7gAAAIUBAAATAAAAW0NvbnRlbnRfVHlwZXNdLnhtbHyQz07DMAyH&#xA;70i8Q+QralM4IITa7kDhCAiNB7ASt43WOlEcyvb2pNu4IODoPz9/n1xv9vOkForiPDdwXVagiI23&#xA;jocG3rdPxR0oScgWJ8/UwIEENu3lRb09BBKV0ywNjCmFe63FjDSjlD4Q50nv44wpl3HQAc0OB9I3&#xA;VXWrjedEnIq03oC27qjHjympx31un0wiTQLq4bS4shrAECZnMGVTvbD9QSnOhDInjzsyuiBXWQP0&#xA;r4R18jfgnHvJr4nOknrFmJ5xzhraRtHWf3Kkpfz/yGo5S+H73hkquyhdjr3R8m2lj09svwAAAP//&#xA;AwBQSwMEFAAGAAgAAAAhAFr0LFu/AAAAFQEAAAsAAABfcmVscy8ucmVsc2zPwWrDMAwG4Ptg72B0&#xA;X5TuUMaI01uh19I+gLGVxCy2jGSy9e1nemrHjpL4P0nD4SetZiPRyNnCruvBUPYcYp4tXC/Htw8w&#xA;Wl0ObuVMFm6kcBhfX4Yzra62kC6xqGlKVgtLreUTUf1CyWnHhXKbTCzJ1VbKjMX5LzcTvvf9HuXR&#xA;gPHJNKdgQU5hB+ZyK23zHztFL6w81c5zQp6m6P9TMfB3PtPWFCczVQtB9N4U2rp2HOA44NMz4y8A&#xA;AAD//wMAUEsDBBQABgAIAAAAIQAeexLbwgAAAN4AAAAPAAAAZHJzL2Rvd25yZXYueG1sRE/NSgMx&#xA;EL4LvkMYwZtNLFTWtWlZBNGLiNUHGJNxs7qZLMm0XX16Iwje5uP7nfV2jqM6UC5DYguXCwOK2CU/&#xA;cG/h9eXuogFVBNnjmJgsfFGB7eb0ZI2tT0d+psNOelVDuLRoIYhMrdbFBYpYFmkirtx7yhGlwtxr&#xA;n/FYw+Ool8Zc6YgD14aAE90Gcp+7fbTwJKtvCW+5cU23Xz529zK4D7H2/GzubkAJzfIv/nM/+Drf&#xA;rMw1/L5Tb9CbHwAAAP//AwBQSwECLQAUAAYACAAAACEA2+H2y+4AAACFAQAAEwAAAAAAAAAAAAAA&#xA;AAAAAAAAW0NvbnRlbnRfVHlwZXNdLnhtbFBLAQItABQABgAIAAAAIQBa9CxbvwAAABUBAAALAAAA&#xA;AAAAAAAAAAAAAB8BAABfcmVscy8ucmVsc1BLAQItABQABgAIAAAAIQAeexLbwgAAAN4AAAAPAAAA&#xA;AAAAAAAAAAAAAAcCAABkcnMvZG93bnJldi54bWxQSwUGAAAAAAMAAwC3AAAA9gIAAAAA&#xA;" path="m,l7560005,r,216002l,216002,,e" fillcolor="#0070a3" stroked="f" strokeweight="0"><v:stroke miterlimit="83231f" joinstyle="miter"/><v:path arrowok="t" textboxrect="0,0,7560005,216002"/></v:shape><w10:wrap type="topAndBottom" anchorx="page" anchory="page"/></v:group></w:pict></mc:Fallback></mc:AlternateContent></w:r><w:r><w:t>8.3 Where the Buyer has accepted, or has been deemed to have accepted, the Goods the Buyer shall not be entitled to reject Goods which are not in accordance with the contract.</w:t></w:r></w:p><w:p w14:paraId="0B960DE0" w14:textId="77777777" w:rsidR="00EF5116" w:rsidRDefault="00000000"><w:pPr><w:pStyle w:val="Heading2"/><w:ind w:left="-5"/></w:pPr><w:r><w:t>9. Title and risk</w:t></w:r></w:p><w:p w14:paraId="169F11A2" w14:textId="77777777" w:rsidR="00EF5116" w:rsidRDefault="00000000"><w:pPr><w:ind w:left="-5"/></w:pPr><w:r><w:t>9.1 Risk shall pass on delivery of the Goods to the Buyer’s address.</w:t></w:r></w:p><w:p w14:paraId="6F7443B9" w14:textId="77777777" w:rsidR="00EF5116" w:rsidRDefault="00000000"><w:pPr><w:ind w:left="-5"/></w:pPr><w:r><w:t>9.2 Notwithstanding the earlier passing of risk, title in the Goods shall remain with the Seller and shall not pass to the Buyer until the amount due under the invoice for them (including interest and costs) has been paid in full.</w:t></w:r></w:p><w:p w14:paraId="5A57022C" w14:textId="77777777" w:rsidR="00EF5116" w:rsidRDefault="00000000"><w:pPr><w:spacing w:after="0"/><w:ind w:left="-5"/></w:pPr><w:r><w:lastRenderedPageBreak/><w:t xml:space="preserve">9.3 Until title passes the Buyer shall hold the Goods as bailee for the Seller and shall store or mark them so that they </w:t></w:r><w:proofErr w:type="gramStart"/><w:r><w:t>can at all times</w:t></w:r><w:proofErr w:type="gramEnd"/><w:r><w:t xml:space="preserve"> be identified as the property of the</w:t></w:r></w:p><w:p w14:paraId="56FB3676" w14:textId="77777777" w:rsidR="00EF5116" w:rsidRDefault="00000000"><w:pPr><w:ind w:left="-5"/></w:pPr><w:r><w:t>Seller.</w:t></w:r></w:p><w:p w14:paraId="7E653CF5" w14:textId="77777777" w:rsidR="00EF5116" w:rsidRDefault="00000000"><w:pPr><w:ind w:left="-5"/></w:pPr><w:r><w:t>9.4 The Seller may at any time before title passes and without any liability to the Buyer:</w:t></w:r></w:p><w:p w14:paraId="0CE07905" w14:textId="77777777" w:rsidR="00EF5116" w:rsidRDefault="00000000"><w:pPr><w:ind w:left="-5"/></w:pPr><w:r><w:t>9.4.1 repossess and dismantle and use or sell all or any of the Goods and by doing so terminate the Buyer’s right to use, sell or otherwise deal in them; and</w:t></w:r></w:p><w:p w14:paraId="1A8F6B97" w14:textId="77777777" w:rsidR="00EF5116" w:rsidRDefault="00000000"><w:pPr><w:spacing w:after="118"/><w:ind w:left="-5"/></w:pPr><w:r><w:t>9.4.2 for that purpose (or determining what if any Goods are held by the Buyer and inspecting them) enter any premises of or occupied by the Buyer.</w:t></w:r></w:p><w:p w14:paraId="0B1F513B" w14:textId="77777777" w:rsidR="00EF5116" w:rsidRDefault="00000000"><w:pPr><w:spacing w:after="491"/><w:ind w:left="-5"/></w:pPr><w:r><w:t>9.5 The Seller may maintain an action for the price of any Goods notwithstanding that title in them has not passed to the Buyer.</w:t></w:r></w:p><w:p w14:paraId="4B7C01F3" w14:textId="77777777" w:rsidR="00EF5116" w:rsidRDefault="00000000"><w:pPr><w:pStyle w:val="Heading2"/><w:ind w:left="-5"/></w:pPr><w:r><w:t>10. Carriage of Goods</w:t></w:r></w:p><w:p w14:paraId="6F63A5FC" w14:textId="77777777" w:rsidR="00EF5116" w:rsidRDefault="00000000"><w:pPr><w:ind w:left="-5"/></w:pPr><w:r><w:t>Carriage will be chargeable on all sales unless otherwise stated.</w:t></w:r></w:p><w:sectPr w:rsidR="00EF5116" w:rsidSect="006E73FE"><w:type w:val="continuous"/><w:pgSz w:w="11906" w:h="16838"/><w:pgMar w:top="815" w:right="851" w:bottom="312" w:left="850" w:header="720" w:footer="720" w:gutter="0"/><w:cols w:space="234"/></w:sectPr></w:body></w:document>